<?xml version="1.0" encoding="ISO-8859-1"?>
<modeling>
 <generator>
  <i name="program" type="string">vasp </i>
  <i name="version" type="string">6.1.0  </i>
  <i name="subversion" type="string">28Jan20 (build Mar 31 2020 17:42:31) gamma-only                       parallel </i>
  <i name="platform" type="string">LinuxIFC </i>
  <i name="date" type="string">2020 04 12 </i>
  <i name="time" type="string">10:07:18 </i>
 </generator>
 <incar>
  <i type="string" name="SYSTEM">"Millerite NiS"</i>
  <i type="int" name="NSIM">     4</i>
  <i type="int" name="NELM">   100</i>
  <i name="ENCUT">    450.00000000</i>
  <i type="string" name="LREAL">A</i>
  <i type="int" name="ISMEAR">     0</i>
  <i type="int" name="NWRITE">     2</i>
  <i type="logical" name="LWAVE"> F  </i>
  <i type="logical" name="LCHARG"> F  </i>
  <i type="int" name="NCORE">     6</i>
  <i type="int" name="NELM">   100</i>
 </incar>
 <structure name="primitive_cell" >
  <crystal>
   <varray name="basis" >
    <v>      16.88469405       0.00000000       0.00000000 </v>
    <v>       0.00000000       9.57841000       0.00000000 </v>
    <v>       0.00000000       0.00000000      16.16908712 </v>
   </varray>
   <i name="volume">   2615.00256803 </i>
   <varray name="rec_basis" >
    <v>       0.05922524       0.00000000       0.00000000 </v>
    <v>       0.00000000       0.10440146       0.00000000 </v>
    <v>       0.00000000       0.00000000       0.06184641 </v>
   </varray>
  </crystal>
  <varray name="positions" >
   <v>       0.78004631       0.14529695       0.12058499 </v>
   <v>       0.26276233       0.64529695       0.02520102 </v>
   <v>       0.29733029       0.64529695       0.21596897 </v>
   <v>       0.43519032       0.14529695       0.05699568 </v>
   <v>       0.46975828       0.14529695       0.24776362 </v>
   <v>       0.95247430       0.64529695       0.15237965 </v>
   <v>       0.98704226       0.64529695       0.34314760 </v>
   <v>       0.12490229       0.14529695       0.18417431 </v>
   <v>       0.15947025       0.14529695       0.37494226 </v>
   <v>       0.60761831       0.64529695       0.08879033 </v>
   <v>       0.64218627       0.64529695       0.27955828 </v>
   <v>       0.90758278       0.01319395       0.09538397 </v>
   <v>       0.94215073       0.01319395       0.28615192 </v>
   <v>       0.39029880       0.51319395       0.00000000 </v>
   <v>       0.42486675       0.51319395       0.19076795 </v>
   <v>       0.45943471       0.51319395       0.38153589 </v>
   <v>       0.56272679       0.01319395       0.03179466 </v>
   <v>       0.59729475       0.01319395       0.22256261 </v>
   <v>       0.08001077       0.51319395       0.12717863 </v>
   <v>       0.11457873       0.51319395       0.31794658 </v>
   <v>       0.25243876       0.01319395       0.15897329 </v>
   <v>       0.28700672       0.01319395       0.34974124 </v>
   <v>       0.73515478       0.51319395       0.06358932 </v>
   <v>       0.76972274       0.51319395       0.25435726 </v>
   <v>       0.90758278       0.27739995       0.09538397 </v>
   <v>       0.94215073       0.27739995       0.28615192 </v>
   <v>       0.39029880       0.77739995       0.00000000 </v>
   <v>       0.42486675       0.77739995       0.19076795 </v>
   <v>       0.45943471       0.77739995       0.38153589 </v>
   <v>       0.56272679       0.27739995       0.03179466 </v>
   <v>       0.59729475       0.27739995       0.22256261 </v>
   <v>       0.08001077       0.77739995       0.12717863 </v>
   <v>       0.11457873       0.77739995       0.31794658 </v>
   <v>       0.25243876       0.27739995       0.15897329 </v>
   <v>       0.73515478       0.77739995       0.06358932 </v>
   <v>       0.76972274       0.77739995       0.25435726 </v>
   <v>       0.02602916       0.14529695       0.37317765 </v>
   <v>       0.99146121       0.14529695       0.18240970 </v>
   <v>       0.47417723       0.64529695       0.08702573 </v>
   <v>       0.50874518       0.64529695       0.27779368 </v>
   <v>       0.64660522       0.14529695       0.11882039 </v>
   <v>       0.68117318       0.14529695       0.30958834 </v>
   <v>       0.12932124       0.64529695       0.02343641 </v>
   <v>       0.16388920       0.64529695       0.21420436 </v>
   <v>       0.30174923       0.14529695       0.05523107 </v>
   <v>       0.33631719       0.14529695       0.24599902 </v>
   <v>       0.81903321       0.64529695       0.15061505 </v>
   <v>       0.85360117       0.64529695       0.34138299 </v>
   <v>       0.79449310       0.31351195       0.02373179 </v>
   <v>       0.82906105       0.31351195       0.21449973 </v>
   <v>       0.31177708       0.81351195       0.11911576 </v>
   <v>       0.34634503       0.81351195       0.30988371 </v>
   <v>       0.48420507       0.31351195       0.15091042 </v>
   <v>       0.51877303       0.31351195       0.34167837 </v>
   <v>       0.00148905       0.81351195       0.24629439 </v>
   <v>       0.96692109       0.81351195       0.05552644 </v>
   <v>       0.13934908       0.31351195       0.08732110 </v>
   <v>       0.17391704       0.31351195       0.27808905 </v>
   <v>       0.65663306       0.81351195       0.18270508 </v>
   <v>       0.69120102       0.81351195       0.37347302 </v>
   <v>       0.31177708       0.47708195       0.11911576 </v>
   <v>       0.34634503       0.47708195       0.30988371 </v>
   <v>       0.79449310       0.97708195       0.02373179 </v>
   <v>       0.82906105       0.97708195       0.21449973 </v>
   <v>       0.00148905       0.47708195       0.24629439 </v>
   <v>       0.96692109       0.47708195       0.05552644 </v>
   <v>       0.48420507       0.97708195       0.15091042 </v>
   <v>       0.51877303       0.97708195       0.34167837 </v>
   <v>       0.65663306       0.47708195       0.18270508 </v>
   <v>       0.69120102       0.47708195       0.37347302 </v>
   <v>       0.13934908       0.97708195       0.08732110 </v>
   <v>       0.17391704       0.97708195       0.27808905 </v>
  </varray>
 </structure>
 <varray name="primitive_index" >
  <v type="int" >        1 </v>
  <v type="int" >        2 </v>
  <v type="int" >        3 </v>
  <v type="int" >        4 </v>
  <v type="int" >        5 </v>
  <v type="int" >        6 </v>
  <v type="int" >        7 </v>
  <v type="int" >        8 </v>
  <v type="int" >        9 </v>
  <v type="int" >       10 </v>
  <v type="int" >       11 </v>
  <v type="int" >       12 </v>
  <v type="int" >       13 </v>
  <v type="int" >       14 </v>
  <v type="int" >       15 </v>
  <v type="int" >       16 </v>
  <v type="int" >       17 </v>
  <v type="int" >       18 </v>
  <v type="int" >       19 </v>
  <v type="int" >       20 </v>
  <v type="int" >       21 </v>
  <v type="int" >       22 </v>
  <v type="int" >       23 </v>
  <v type="int" >       24 </v>
  <v type="int" >       25 </v>
  <v type="int" >       26 </v>
  <v type="int" >       27 </v>
  <v type="int" >       28 </v>
  <v type="int" >       29 </v>
  <v type="int" >       30 </v>
  <v type="int" >       31 </v>
  <v type="int" >       32 </v>
  <v type="int" >       33 </v>
  <v type="int" >       34 </v>
  <v type="int" >       35 </v>
  <v type="int" >       36 </v>
  <v type="int" >       37 </v>
  <v type="int" >       38 </v>
  <v type="int" >       39 </v>
  <v type="int" >       40 </v>
  <v type="int" >       41 </v>
  <v type="int" >       42 </v>
  <v type="int" >       43 </v>
  <v type="int" >       44 </v>
  <v type="int" >       45 </v>
  <v type="int" >       46 </v>
  <v type="int" >       47 </v>
  <v type="int" >       48 </v>
  <v type="int" >       49 </v>
  <v type="int" >       50 </v>
  <v type="int" >       51 </v>
  <v type="int" >       52 </v>
  <v type="int" >       53 </v>
  <v type="int" >       54 </v>
  <v type="int" >       55 </v>
  <v type="int" >       56 </v>
  <v type="int" >       57 </v>
  <v type="int" >       58 </v>
  <v type="int" >       59 </v>
  <v type="int" >       60 </v>
  <v type="int" >       61 </v>
  <v type="int" >       62 </v>
  <v type="int" >       63 </v>
  <v type="int" >       64 </v>
  <v type="int" >       65 </v>
  <v type="int" >       66 </v>
  <v type="int" >       67 </v>
  <v type="int" >       68 </v>
  <v type="int" >       69 </v>
  <v type="int" >       70 </v>
  <v type="int" >       71 </v>
  <v type="int" >       72 </v>
 </varray>
 <kpoints>
  <generation param="Gamma">
   <v type="int" name="divisions">       1        1        1 </v>
   <v name="usershift">      0.00000000       0.00000000       0.00000000 </v>
   <v name="genvec1">      1.00000000       0.00000000       0.00000000 </v>
   <v name="genvec2">      0.00000000       1.00000000       0.00000000 </v>
   <v name="genvec3">      0.00000000       0.00000000       1.00000000 </v>
   <v name="shift">      0.00000000       0.00000000       0.00000000 </v>
  </generation>
  <varray name="kpointlist" >
   <v>       0.00000000       0.00000000       0.00000000 </v>
  </varray>
  <varray name="weights" >
   <v>       1.00000000 </v>
  </varray>
 </kpoints>
 <parameters>
  <separator name="general" >
   <i type="string" name="SYSTEM">"Millerite NiS"</i>
   <i type="logical" name="LCOMPAT"> F  </i>
  </separator>
  <separator name="electronic" >
   <i type="string" name="PREC">normal</i>
   <i name="ENMAX">    450.00000000</i>
   <i name="ENAUG">    703.44300000</i>
   <i name="EDIFF">      0.00010000</i>
   <i type="int" name="IALGO">    38</i>
   <i type="int" name="IWAVPR">    10</i>
   <i type="int" name="NBANDS">   480</i>
   <i type="int" name="NBANDSLOW">    -1</i>
   <i type="int" name="NBANDSHIGH">    -1</i>
   <i name="NELECT">    792.00000000</i>
   <i type="int" name="TURBO">     0</i>
   <i type="int" name="IRESTART">     0</i>
   <i type="int" name="NREBOOT">     0</i>
   <i type="int" name="NMIN">     0</i>
   <i name="EREF">      0.00000000</i>
   <separator name="electronic smearing" >
    <i type="int" name="ISMEAR">     0</i>
    <i name="SIGMA">      0.20000000</i>
    <i name="KSPACING">      0.50000000</i>
    <i type="logical" name="KGAMMA"> T  </i>
    <i type="logical" name="KBLOWUP"> T  </i>
   </separator>
   <separator name="electronic projectors" >
    <i type="logical" name="LREAL"> T  </i>
    <v name="ROPT">     -0.00050000     -0.00050000</v>
    <i type="int" name="LMAXPAW">  -100</i>
    <i type="int" name="LMAXMIX">     2</i>
    <i type="logical" name="NLSPLINE"> F  </i>
   </separator>
   <separator name="electronic startup" >
    <i type="int" name="ISTART">     0</i>
    <i type="int" name="ICHARG">     2</i>
    <i type="int" name="INIWAV">     1</i>
   </separator>
   <separator name="electronic spin" >
    <i type="int" name="ISPIN">     1</i>
    <i type="logical" name="LNONCOLLINEAR"> F  </i>
    <v name="MAGMOM">      1.00000000      1.00000000      1.00000000      1.00000000      1.00000000      1.00000000      1.00000000      1.00000000      1.00000000      1.00000000      1.00000000      1.00000000      1.00000000      1.00000000      1.00000000      1.00000000      1.00000000      1.00000000      1.00000000      1.00000000
      1.00000000      1.00000000      1.00000000      1.00000000      1.00000000      1.00000000      1.00000000      1.00000000      1.00000000      1.00000000      1.00000000      1.00000000      1.00000000      1.00000000      1.00000000      1.00000000      1.00000000      1.00000000      1.00000000      1.00000000
      1.00000000      1.00000000      1.00000000      1.00000000      1.00000000      1.00000000      1.00000000      1.00000000      1.00000000      1.00000000      1.00000000      1.00000000      1.00000000      1.00000000      1.00000000      1.00000000      1.00000000      1.00000000      1.00000000      1.00000000
      1.00000000      1.00000000      1.00000000      1.00000000      1.00000000      1.00000000      1.00000000      1.00000000      1.00000000      1.00000000      1.00000000      1.00000000</v>
    <i name="NUPDOWN">     -1.00000000</i>
    <i type="logical" name="LSORBIT"> F  </i>
    <v name="SAXIS">      0.00000000      0.00000000      1.00000000</v>
    <i type="logical" name="LSPIRAL"> F  </i>
    <v name="QSPIRAL">      0.00000000      0.00000000      0.00000000</v>
    <i type="logical" name="LZEROZ"> F  </i>
   </separator>
   <separator name="electronic exchange-correlation" >
    <i type="logical" name="LASPH"> F  </i>
    <i type="logical" name="LMETAGGA"> F  </i>
   </separator>
   <separator name="electronic convergence" >
    <i type="int" name="NELM">   100</i>
    <i type="int" name="NELMDL">    -5</i>
    <i type="int" name="NELMIN">     2</i>
    <i name="ENINI">    450.00000000</i>
    <separator name="electronic convergence detail" >
     <i type="logical" name="LDIAG"> T  </i>
     <i type="logical" name="LSUBROT"> F  </i>
     <i name="WEIMIN">      0.00000000</i>
     <i name="EBREAK">      0.00000005</i>
     <i name="DEPER">      0.30000000</i>
     <i type="int" name="NRMM">     4</i>
     <i name="TIME">      0.40000000</i>
    </separator>
   </separator>
   <separator name="electronic mixer" >
    <i name="AMIX">      0.40000000</i>
    <i name="BMIX">      1.00000000</i>
    <i name="AMIN">      0.10000000</i>
    <i name="AMIX_MAG">      1.60000000</i>
    <i name="BMIX_MAG">      1.00000000</i>
    <separator name="electronic mixer details" >
     <i type="int" name="IMIX">     4</i>
     <i type="logical" name="MIXFIRST"> F  </i>
     <i type="int" name="MAXMIX">   -45</i>
     <i name="WC">    100.00000000</i>
     <i type="int" name="INIMIX">     1</i>
     <i type="int" name="MIXPRE">     1</i>
     <i type="int" name="MREMOVE">     5</i>
    </separator>
   </separator>
   <separator name="electronic dipolcorrection" >
    <i type="logical" name="LDIPOL"> F  </i>
    <i type="logical" name="LMONO"> F  </i>
    <i type="int" name="IDIPOL">     0</i>
    <i name="EPSILON">      1.00000000</i>
    <v name="DIPOL">   -100.00000000   -100.00000000   -100.00000000</v>
    <i name="EFIELD">      0.00000000</i>
   </separator>
  </separator>
  <separator name="grids" >
   <i type="int" name="NGX">    90</i>
   <i type="int" name="NGY">    50</i>
   <i type="int" name="NGZ">    84</i>
   <i type="int" name="NGXF">   180</i>
   <i type="int" name="NGYF">   100</i>
   <i type="int" name="NGZF">   168</i>
   <i type="logical" name="ADDGRID"> F  </i>
  </separator>
  <separator name="ionic" >
   <i type="int" name="NSW">     0</i>
   <i type="int" name="IBRION">    -1</i>
   <i type="int" name="MDALGO">     0</i>
   <i type="int" name="ISIF">     2</i>
   <i name="PSTRESS">      0.00000000</i>
   <i name="EDIFFG">      0.00100000</i>
   <i type="int" name="NFREE">     0</i>
   <i name="POTIM">      0.50000000</i>
   <i name="SMASS">     -3.00000000</i>
   <i name="SCALEE">      1.00000000</i>
  </separator>
  <separator name="ionic md" >
   <i name="TEBEG">      0.00010000</i>
   <i name="TEEND">      0.00010000</i>
   <i type="int" name="NBLOCK">     1</i>
   <i type="int" name="KBLOCK">     1</i>
   <i type="int" name="NPACO">   256</i>
   <i name="APACO">     16.00000000</i>
  </separator>
  <separator name="symmetry" >
   <i type="int" name="ISYM">     2</i>
   <i name="SYMPREC">      0.00001000</i>
  </separator>
  <separator name="dos" >
   <i type="int" name="LORBIT">     0</i>
   <v name="RWIGS">     -1.00000000     -1.00000000</v>
   <i type="int" name="NEDOS">   301</i>
   <i name="EMIN">     10.00000000</i>
   <i name="EMAX">    -10.00000000</i>
   <i name="EFERMI">      0.00000000</i>
  </separator>
  <separator name="writing" >
   <i type="int" name="NWRITE">     2</i>
   <i type="logical" name="LWAVE"> F  </i>
   <i type="logical" name="LDOWNSAMPLE"> F  </i>
   <i type="logical" name="LCHARG"> F  </i>
   <i type="logical" name="LPARD"> F  </i>
   <i type="logical" name="LVTOT"> F  </i>
   <i type="logical" name="LVHAR"> F  </i>
   <i type="logical" name="LELF"> F  </i>
   <i type="logical" name="LOPTICS"> F  </i>
   <v name="STM">      0.00000000      0.00000000      0.00000000      0.00000000      0.00000000      0.00000000      0.00000000</v>
  </separator>
  <separator name="performance" >
   <i type="int" name="NPAR">     8</i>
   <i type="int" name="NSIM">     4</i>
   <i type="int" name="NBLK">    -1</i>
   <i type="logical" name="LPLANE"> T  </i>
   <i type="logical" name="LSCALAPACK"> T  </i>
   <i type="logical" name="LSCAAWARE"> F  </i>
   <i type="logical" name="LSCALU"> F  </i>
   <i type="logical" name="LASYNC"> F  </i>
   <i type="logical" name="LORBITALREAL"> F  </i>
  </separator>
  <separator name="miscellaneous" >
   <i type="int" name="IDIOT">     3</i>
   <i type="int" name="PHON_NSTRUCT">    -1</i>
   <i type="logical" name="LMUSIC"> F  </i>
   <v name="POMASS">     58.69000000     32.06600000</v>
   <v name="DARWINR">      0.00000000      0.00000000</v>
   <v name="DARWINV">      1.00000000      1.00000000</v>
   <i type="logical" name="LCORR"> T  </i>
  </separator>
  <i type="logical" name="GGA_COMPAT"> T  </i>
  <i type="logical" name="LBERRY"> F  </i>
  <i type="int" name="ICORELEVEL">     0</i>
  <i type="logical" name="LDAU"> F  </i>
  <i type="int" name="I_CONSTRAINED_M">     0</i>
  <separator name="electronic exchange-correlation" >
   <i type="string" name="GGA">--</i>
   <i type="int" name="VOSKOWN">     0</i>
   <i type="logical" name="LHFCALC"> F  </i>
   <i type="string" name="PRECFOCK"></i>
   <i type="logical" name="LSYMGRAD"> F  </i>
   <i type="logical" name="LHFONE"> F  </i>
   <i type="logical" name="LRHFCALC"> F  </i>
   <i type="logical" name="LTHOMAS"> F  </i>
   <i type="logical" name="LMODELHF"> F  </i>
   <i type="logical" name="LFOCKACE"> F  </i>
   <i name="ENCUT4O">     -1.00000000</i>
   <i type="int" name="EXXOEP">     0</i>
   <i type="int" name="FOURORBIT">     0</i>
   <i name="AEXX">      0.00000000</i>
   <i name="HFALPHA">      0.00000000</i>
   <i name="MCALPHA">      0.00000000</i>
   <i name="ALDAX">      1.00000000</i>
   <i name="AGGAX">      1.00000000</i>
   <i name="ALDAC">      1.00000000</i>
   <i name="AGGAC">      1.00000000</i>
   <i type="int" name="NKREDX">     1</i>
   <i type="int" name="NKREDY">     1</i>
   <i type="int" name="NKREDZ">     1</i>
   <i type="logical" name="SHIFTRED"> F  </i>
   <i type="logical" name="ODDONLY"> F  </i>
   <i type="logical" name="EVENONLY"> F  </i>
   <i type="int" name="LMAXFOCK">     0</i>
   <i type="int" name="NMAXFOCKAE">     0</i>
   <i type="logical" name="LFOCKAEDFT"> F  </i>
   <i name="HFSCREEN">      0.00000000</i>
   <i name="HFSCREENC">      0.00000000</i>
   <i type="int" name="NBANDSGWLOW">     0</i>
  </separator>
  <separator name="vdW DFT" >
   <i type="logical" name="LUSE_VDW"> F  </i>
   <i name="Zab_VDW">     -0.84910000</i>
   <i name="PARAM1">      0.12340000</i>
   <i name="PARAM2">      1.00000000</i>
   <i name="PARAM3">      0.00000000</i>
  </separator>
  <separator name="model GW" >
   <i type="int" name="MODEL_GW">     0</i>
   <i name="MODEL_EPS0">     21.79168807</i>
   <i name="MODEL_ALPHA">      1.00000000</i>
  </separator>
  <separator name="linear response parameters" >
   <i type="logical" name="LEPSILON"> F  </i>
   <i type="logical" name="LRPA"> F  </i>
   <i type="logical" name="LNABLA"> F  </i>
   <i type="logical" name="LVEL"> F  </i>
   <i type="int" name="KINTER">     0</i>
   <i name="CSHIFT">      0.10000000</i>
   <i name="OMEGAMAX">     -1.00000000</i>
   <i name="DEG_THRESHOLD">      0.00200000</i>
   <i name="RTIME">     -0.10000000</i>
   <i name="WPLASMAI">      0.00000000</i>
   <v name="DFIELD">      0.00000000      0.00000000      0.00000000</v>
   <v name="WPLASMA">      0.00000000      0.00000000      0.00000000      0.00000000      0.00000000      0.00000000      0.00000000      0.00000000      0.00000000</v>
  </separator>
  <separator name="orbital magnetization" >
   <i type="logical" name="NUCIND"> F  </i>
   <v name="MAGPOS">      0.00000000      0.00000000      0.00000000</v>
   <i type="logical" name="LNICSALL"> T  </i>
   <i type="logical" name="ORBITALMAG"> F  </i>
   <i type="logical" name="LMAGBLOCH"> F  </i>
   <i type="logical" name="LCHIMAG"> F  </i>
   <i type="logical" name="LGAUGE"> T  </i>
   <i type="int" name="MAGATOM">     0</i>
   <v name="MAGDIPOL">      0.00000000      0.00000000      0.00000000</v>
   <v name="AVECCONST">      0.00000000      0.00000000      0.00000000</v>
  </separator>
  <separator name="response functions" >
   <i type="logical" name="LFINITE_TEMPERATURE"> F  </i>
   <i type="logical" name="LADDER"> F  </i>
   <i type="logical" name="LRPAFORCE"> F  </i>
   <i type="logical" name="LFXC"> F  </i>
   <i type="logical" name="LHARTREE"> T  </i>
   <i type="int" name="IBSE">     0</i>
   <v type="int" name="KPOINT">    -1     0     0     0</v>
   <i type="logical" name="LTCTC"> F  </i>
   <i type="logical" name="LTCTE"> F  </i>
   <i type="logical" name="LTETE"> F  </i>
   <i type="logical" name="LTRIPLET"> F  </i>
   <i type="logical" name="LFXCEPS"> F  </i>
   <i type="logical" name="LFXHEG"> F  </i>
   <i type="int" name="NATURALO">     2</i>
   <i type="logical" name="LHOLEGF"> F  </i>
   <i type="logical" name="L2ORDER"> F  </i>
   <i type="logical" name="LDMP1"> F  </i>
   <i type="logical" name="LMP2LT"> F  </i>
   <i type="logical" name="LSMP2LT"> F  </i>
   <i type="logical" name="LGWLF"> F  </i>
   <i name="ENCUTGW">     -2.00000000</i>
   <i name="ENCUTGWSOFT">     -2.00000000</i>
   <i name="ENCUTLF">     -1.00000000</i>
   <i type="logical" name="LESF_SPLINES"> F  </i>
   <i type="int" name="LMAXMP2">    -1</i>
   <i name="SCISSOR">      0.00000000</i>
   <i type="int" name="NOMEGA">     0</i>
   <i type="int" name="NOMEGAR">     0</i>
   <i type="int" name="NBANDSGW">    -1</i>
   <i type="int" name="NBANDSO">    -1</i>
   <i type="int" name="NBANDSV">    -1</i>
   <i type="int" name="NELM">   100</i>
   <i type="int" name="NELMHF">     1</i>
   <i type="int" name="DIM">     3</i>
   <i type="int" name="IESPILON">     4</i>
   <i type="int" name="ANTIRES">     0</i>
   <i name="OMEGAMAX">    -30.00000000</i>
   <i name="OMEGAMIN">    -30.00000000</i>
   <i name="OMEGATL">   -200.00000000</i>
   <i type="int" name="OMEGAGRID">     0</i>
   <i name="CSHIFT">     -0.10000000</i>
   <i type="logical" name="LSELFENERGY"> F  </i>
   <i type="logical" name="LSPECTRAL"> F  </i>
   <i type="logical" name="LSPECTRALGW"> F  </i>
   <i type="logical" name="LSINGLES"> F  </i>
   <i type="logical" name="LFERMIGW"> F  </i>
   <i type="logical" name="ODDONLYGW"> F  </i>
   <i type="logical" name="EVENONLYGW"> F  </i>
   <i type="int" name="NKREDLFX">     1</i>
   <i type="int" name="NKREDLFY">     1</i>
   <i type="int" name="NKREDLFZ">     1</i>
   <i type="int" name="MAXMEM">  2800</i>
   <i type="int" name="TELESCOPE">     0</i>
   <i type="int" name="NTAUPAR">    -1</i>
   <i type="int" name="NOMEGAPAR">    -1</i>
   <i name="LAMBDA">      1.00000000</i>
  </separator>
  <separator name="External order field" >
   <i name="OFIELD_KAPPA">      0.00000000</i>
   <v name="OFIELD_K">      0.00000000      0.00000000      0.00000000</v>
   <i name="OFIELD_Q6_NEAR">      0.00000000</i>
   <i name="OFIELD_Q6_FAR">      0.00000000</i>
   <i name="OFIELD_A">      0.00000000</i>
  </separator>
 </parameters>
 <atominfo>
  <atoms>      72 </atoms>
  <types>       2 </types>
  <array name="atoms" >
   <dimension dim="1">ion</dimension>
   <field type="string">element</field>
   <field type="int">atomtype</field>
   <set>
    <rc><c>Ni</c><c>   1</c></rc>
    <rc><c>Ni</c><c>   1</c></rc>
    <rc><c>Ni</c><c>   1</c></rc>
    <rc><c>Ni</c><c>   1</c></rc>
    <rc><c>Ni</c><c>   1</c></rc>
    <rc><c>Ni</c><c>   1</c></rc>
    <rc><c>Ni</c><c>   1</c></rc>
    <rc><c>Ni</c><c>   1</c></rc>
    <rc><c>Ni</c><c>   1</c></rc>
    <rc><c>Ni</c><c>   1</c></rc>
    <rc><c>Ni</c><c>   1</c></rc>
    <rc><c>Ni</c><c>   1</c></rc>
    <rc><c>Ni</c><c>   1</c></rc>
    <rc><c>Ni</c><c>   1</c></rc>
    <rc><c>Ni</c><c>   1</c></rc>
    <rc><c>Ni</c><c>   1</c></rc>
    <rc><c>Ni</c><c>   1</c></rc>
    <rc><c>Ni</c><c>   1</c></rc>
    <rc><c>Ni</c><c>   1</c></rc>
    <rc><c>Ni</c><c>   1</c></rc>
    <rc><c>Ni</c><c>   1</c></rc>
    <rc><c>Ni</c><c>   1</c></rc>
    <rc><c>Ni</c><c>   1</c></rc>
    <rc><c>Ni</c><c>   1</c></rc>
    <rc><c>Ni</c><c>   1</c></rc>
    <rc><c>Ni</c><c>   1</c></rc>
    <rc><c>Ni</c><c>   1</c></rc>
    <rc><c>Ni</c><c>   1</c></rc>
    <rc><c>Ni</c><c>   1</c></rc>
    <rc><c>Ni</c><c>   1</c></rc>
    <rc><c>Ni</c><c>   1</c></rc>
    <rc><c>Ni</c><c>   1</c></rc>
    <rc><c>Ni</c><c>   1</c></rc>
    <rc><c>Ni</c><c>   1</c></rc>
    <rc><c>Ni</c><c>   1</c></rc>
    <rc><c>Ni</c><c>   1</c></rc>
    <rc><c>S </c><c>   2</c></rc>
    <rc><c>S </c><c>   2</c></rc>
    <rc><c>S </c><c>   2</c></rc>
    <rc><c>S </c><c>   2</c></rc>
    <rc><c>S </c><c>   2</c></rc>
    <rc><c>S </c><c>   2</c></rc>
    <rc><c>S </c><c>   2</c></rc>
    <rc><c>S </c><c>   2</c></rc>
    <rc><c>S </c><c>   2</c></rc>
    <rc><c>S </c><c>   2</c></rc>
    <rc><c>S </c><c>   2</c></rc>
    <rc><c>S </c><c>   2</c></rc>
    <rc><c>S </c><c>   2</c></rc>
    <rc><c>S </c><c>   2</c></rc>
    <rc><c>S </c><c>   2</c></rc>
    <rc><c>S </c><c>   2</c></rc>
    <rc><c>S </c><c>   2</c></rc>
    <rc><c>S </c><c>   2</c></rc>
    <rc><c>S </c><c>   2</c></rc>
    <rc><c>S </c><c>   2</c></rc>
    <rc><c>S </c><c>   2</c></rc>
    <rc><c>S </c><c>   2</c></rc>
    <rc><c>S </c><c>   2</c></rc>
    <rc><c>S </c><c>   2</c></rc>
    <rc><c>S </c><c>   2</c></rc>
    <rc><c>S </c><c>   2</c></rc>
    <rc><c>S </c><c>   2</c></rc>
    <rc><c>S </c><c>   2</c></rc>
    <rc><c>S </c><c>   2</c></rc>
    <rc><c>S </c><c>   2</c></rc>
    <rc><c>S </c><c>   2</c></rc>
    <rc><c>S </c><c>   2</c></rc>
    <rc><c>S </c><c>   2</c></rc>
    <rc><c>S </c><c>   2</c></rc>
    <rc><c>S </c><c>   2</c></rc>
    <rc><c>S </c><c>   2</c></rc>
   </set>
  </array>
  <array name="atomtypes" >
   <dimension dim="1">type</dimension>
   <field type="int">atomspertype</field>
   <field type="string">element</field>
   <field>mass</field>
   <field>valence</field>
   <field type="string">pseudopotential</field>
   <set>
    <rc><c>  36</c><c>Ni</c><c>     58.69000000</c><c>     16.00000000</c><c>  PAW_PBE Ni_pv 06Sep2000               </c></rc>
    <rc><c>  36</c><c>S </c><c>     32.06600000</c><c>      6.00000000</c><c>  PAW_PBE S 06Sep2000                   </c></rc>
   </set>
  </array>
 </atominfo>
 <structure name="initialpos" >
  <crystal>
   <varray name="basis" >
    <v>      16.88469405       0.00000000       0.00000000 </v>
    <v>       0.00000000       9.57841000       0.00000000 </v>
    <v>       0.00000000       0.00000000      16.16908712 </v>
   </varray>
   <i name="volume">   2615.00256803 </i>
   <varray name="rec_basis" >
    <v>       0.05922524       0.00000000       0.00000000 </v>
    <v>       0.00000000       0.10440146       0.00000000 </v>
    <v>       0.00000000       0.00000000       0.06184641 </v>
   </varray>
  </crystal>
  <varray name="positions" >
   <v>       0.78004631       0.14529695       0.12058499 </v>
   <v>       0.26276233       0.64529695       0.02520102 </v>
   <v>       0.29733029       0.64529695       0.21596897 </v>
   <v>       0.43519032       0.14529695       0.05699568 </v>
   <v>       0.46975828       0.14529695       0.24776362 </v>
   <v>       0.95247430       0.64529695       0.15237965 </v>
   <v>       0.98704226       0.64529695       0.34314760 </v>
   <v>       0.12490229       0.14529695       0.18417431 </v>
   <v>       0.15947025       0.14529695       0.37494226 </v>
   <v>       0.60761831       0.64529695       0.08879033 </v>
   <v>       0.64218627       0.64529695       0.27955828 </v>
   <v>       0.90758278       0.01319395       0.09538397 </v>
   <v>       0.94215073       0.01319395       0.28615192 </v>
   <v>       0.39029880       0.51319395       0.00000000 </v>
   <v>       0.42486675       0.51319395       0.19076795 </v>
   <v>       0.45943471       0.51319395       0.38153589 </v>
   <v>       0.56272679       0.01319395       0.03179466 </v>
   <v>       0.59729475       0.01319395       0.22256261 </v>
   <v>       0.08001077       0.51319395       0.12717863 </v>
   <v>       0.11457873       0.51319395       0.31794658 </v>
   <v>       0.25243876       0.01319395       0.15897329 </v>
   <v>       0.28700672       0.01319395       0.34974124 </v>
   <v>       0.73515478       0.51319395       0.06358932 </v>
   <v>       0.76972274       0.51319395       0.25435726 </v>
   <v>       0.90758278       0.27739995       0.09538397 </v>
   <v>       0.94215073       0.27739995       0.28615192 </v>
   <v>       0.39029880       0.77739995       0.00000000 </v>
   <v>       0.42486675       0.77739995       0.19076795 </v>
   <v>       0.45943471       0.77739995       0.38153589 </v>
   <v>       0.56272679       0.27739995       0.03179466 </v>
   <v>       0.59729475       0.27739995       0.22256261 </v>
   <v>       0.08001077       0.77739995       0.12717863 </v>
   <v>       0.11457873       0.77739995       0.31794658 </v>
   <v>       0.25243876       0.27739995       0.15897329 </v>
   <v>       0.73515478       0.77739995       0.06358932 </v>
   <v>       0.76972274       0.77739995       0.25435726 </v>
   <v>       0.02602916       0.14529695       0.37317765 </v>
   <v>       0.99146121       0.14529695       0.18240970 </v>
   <v>       0.47417723       0.64529695       0.08702573 </v>
   <v>       0.50874518       0.64529695       0.27779368 </v>
   <v>       0.64660522       0.14529695       0.11882039 </v>
   <v>       0.68117318       0.14529695       0.30958834 </v>
   <v>       0.12932124       0.64529695       0.02343641 </v>
   <v>       0.16388920       0.64529695       0.21420436 </v>
   <v>       0.30174923       0.14529695       0.05523107 </v>
   <v>       0.33631719       0.14529695       0.24599902 </v>
   <v>       0.81903321       0.64529695       0.15061505 </v>
   <v>       0.85360117       0.64529695       0.34138299 </v>
   <v>       0.79449310       0.31351195       0.02373179 </v>
   <v>       0.82906105       0.31351195       0.21449973 </v>
   <v>       0.31177708       0.81351195       0.11911576 </v>
   <v>       0.34634503       0.81351195       0.30988371 </v>
   <v>       0.48420507       0.31351195       0.15091042 </v>
   <v>       0.51877303       0.31351195       0.34167837 </v>
   <v>       0.00148905       0.81351195       0.24629439 </v>
   <v>       0.96692109       0.81351195       0.05552644 </v>
   <v>       0.13934908       0.31351195       0.08732110 </v>
   <v>       0.17391704       0.31351195       0.27808905 </v>
   <v>       0.65663306       0.81351195       0.18270508 </v>
   <v>       0.69120102       0.81351195       0.37347302 </v>
   <v>       0.31177708       0.47708195       0.11911576 </v>
   <v>       0.34634503       0.47708195       0.30988371 </v>
   <v>       0.79449310       0.97708195       0.02373179 </v>
   <v>       0.82906105       0.97708195       0.21449973 </v>
   <v>       0.00148905       0.47708195       0.24629439 </v>
   <v>       0.96692109       0.47708195       0.05552644 </v>
   <v>       0.48420507       0.97708195       0.15091042 </v>
   <v>       0.51877303       0.97708195       0.34167837 </v>
   <v>       0.65663306       0.47708195       0.18270508 </v>
   <v>       0.69120102       0.47708195       0.37347302 </v>
   <v>       0.13934908       0.97708195       0.08732110 </v>
   <v>       0.17391704       0.97708195       0.27808905 </v>
  </varray>
 </structure>
 <calculation>
  <scstep>
   <time name="dav">    2.48    2.48</time>
   <time name="total">    2.54    2.55</time>
   <energy>
    <i name="alphaZ">   1422.52235994 </i>
    <i name="ewald"> 102521.60681565 </i>
    <i name="hartreedc">-223392.90450128 </i>
    <i name="XCdc">   3638.50984683 </i>
    <i name="pawpsdc"> 112729.53333415 </i>
    <i name="pawaedc">-117641.51188735 </i>
    <i name="eentropy">     -0.44116456 </i>
    <i name="bandstr">  -6661.60846422 </i>
    <i name="atom"> 136002.60505376 </i>
    <i name="e_fr_energy">   8618.31139292 </i>
    <i name="e_wo_entrp">   8618.75255748 </i>
    <i name="e_0_energy">   8618.53197520 </i>
   </energy>
  </scstep>
  <scstep>
   <time name="dav">    2.24    2.24</time>
   <time name="total">    2.24    2.25</time>
   <energy>
    <i name="e_fr_energy">    451.64492608 </i>
    <i name="e_wo_entrp">    452.61091681 </i>
    <i name="e_0_energy">    452.12792144 </i>
   </energy>
  </scstep>
  <scstep>
   <time name="dav">    2.40    2.41</time>
   <time name="total">    2.41    2.41</time>
   <energy>
    <i name="e_fr_energy">   -350.51028311 </i>
    <i name="e_wo_entrp">   -348.93521985 </i>
    <i name="e_0_energy">   -349.72275148 </i>
   </energy>
  </scstep>
  <scstep>
   <time name="dav">    2.44    2.45</time>
   <time name="total">    2.45    2.45</time>
   <energy>
    <i name="e_fr_energy">   -395.99452452 </i>
    <i name="e_wo_entrp">   -394.37463171 </i>
    <i name="e_0_energy">   -395.18457812 </i>
   </energy>
  </scstep>
  <scstep>
   <time name="dav">    2.48    2.48</time>
   <time name="total">    2.53    2.54</time>
   <energy>
    <i name="e_fr_energy">   -397.33472759 </i>
    <i name="e_wo_entrp">   -395.72279686 </i>
    <i name="e_0_energy">   -396.52876222 </i>
   </energy>
  </scstep>
  <scstep>
   <time name="dav">    2.40    2.41</time>
   <time name="total">    2.51    2.52</time>
   <energy>
    <i name="e_fr_energy">   -515.45439599 </i>
    <i name="e_wo_entrp">   -514.47734019 </i>
    <i name="e_0_energy">   -514.96586809 </i>
   </energy>
  </scstep>
  <scstep>
   <time name="dav">    2.46    2.46</time>
   <time name="total">    2.57    2.58</time>
   <energy>
    <i name="e_fr_energy">   -376.55309708 </i>
    <i name="e_wo_entrp">   -375.27266655 </i>
    <i name="e_0_energy">   -375.91288181 </i>
   </energy>
  </scstep>
  <scstep>
   <time name="dav">    2.88    2.89</time>
   <time name="total">    3.00    3.01</time>
   <energy>
    <i name="e_fr_energy">   -380.63666446 </i>
    <i name="e_wo_entrp">   -379.09269112 </i>
    <i name="e_0_energy">   -379.86467779 </i>
   </energy>
  </scstep>
  <scstep>
   <time name="dav">    2.65    2.66</time>
   <time name="total">    2.76    2.77</time>
   <energy>
    <i name="e_fr_energy">   -362.73960430 </i>
    <i name="e_wo_entrp">   -361.32974917 </i>
    <i name="e_0_energy">   -362.03467673 </i>
   </energy>
  </scstep>
  <scstep>
   <time name="dav">    2.82    2.82</time>
   <time name="total">    2.93    2.94</time>
   <energy>
    <i name="e_fr_energy">   -356.73890671 </i>
    <i name="e_wo_entrp">   -355.06632204 </i>
    <i name="e_0_energy">   -355.90261437 </i>
   </energy>
  </scstep>
  <scstep>
   <time name="dav">    2.82    2.83</time>
   <time name="total">    2.93    2.94</time>
   <energy>
    <i name="e_fr_energy">   -371.45093192 </i>
    <i name="e_wo_entrp">   -370.04128746 </i>
    <i name="e_0_energy">   -370.74610969 </i>
   </energy>
  </scstep>
  <scstep>
   <time name="dav">    2.84    2.85</time>
   <time name="total">    2.95    2.96</time>
   <energy>
    <i name="e_fr_energy">   -354.15268367 </i>
    <i name="e_wo_entrp">   -352.85611862 </i>
    <i name="e_0_energy">   -353.50440114 </i>
   </energy>
  </scstep>
  <scstep>
   <time name="dav">    2.77    2.78</time>
   <time name="total">    2.88    2.89</time>
   <energy>
    <i name="e_fr_energy">   -348.69195473 </i>
    <i name="e_wo_entrp">   -347.59211286 </i>
    <i name="e_0_energy">   -348.14203379 </i>
   </energy>
  </scstep>
  <scstep>
   <time name="dav">    2.77    2.78</time>
   <time name="total">    2.88    2.89</time>
   <energy>
    <i name="e_fr_energy">   -347.74681840 </i>
    <i name="e_wo_entrp">   -346.33019775 </i>
    <i name="e_0_energy">   -347.03850808 </i>
   </energy>
  </scstep>
  <scstep>
   <time name="dav">    2.77    2.78</time>
   <time name="total">    2.88    2.89</time>
   <energy>
    <i name="e_fr_energy">   -345.49616815 </i>
    <i name="e_wo_entrp">   -344.34199858 </i>
    <i name="e_0_energy">   -344.91908336 </i>
   </energy>
  </scstep>
  <scstep>
   <time name="dav">    2.65    2.66</time>
   <time name="total">    2.76    2.76</time>
   <energy>
    <i name="e_fr_energy">   -344.28478178 </i>
    <i name="e_wo_entrp">   -343.01920386 </i>
    <i name="e_0_energy">   -343.65199282 </i>
   </energy>
  </scstep>
  <scstep>
   <time name="dav">    2.64    2.64</time>
   <time name="total">    2.74    2.75</time>
   <energy>
    <i name="e_fr_energy">   -343.80028716 </i>
    <i name="e_wo_entrp">   -342.51642793 </i>
    <i name="e_0_energy">   -343.15835754 </i>
   </energy>
  </scstep>
  <scstep>
   <time name="dav">    2.74    2.75</time>
   <time name="total">    2.85    2.86</time>
   <energy>
    <i name="e_fr_energy">   -343.42354882 </i>
    <i name="e_wo_entrp">   -342.13977954 </i>
    <i name="e_0_energy">   -342.78166418 </i>
   </energy>
  </scstep>
  <scstep>
   <time name="dav">    2.72    2.73</time>
   <time name="total">    2.83    2.83</time>
   <energy>
    <i name="e_fr_energy">   -343.19838961 </i>
    <i name="e_wo_entrp">   -341.83862393 </i>
    <i name="e_0_energy">   -342.51850677 </i>
   </energy>
  </scstep>
  <scstep>
   <time name="dav">    2.56    2.56</time>
   <time name="total">    2.66    2.67</time>
   <energy>
    <i name="e_fr_energy">   -343.13660934 </i>
    <i name="e_wo_entrp">   -341.77768750 </i>
    <i name="e_0_energy">   -342.45714842 </i>
   </energy>
  </scstep>
  <scstep>
   <time name="dav">    2.65    2.65</time>
   <time name="total">    2.75    2.76</time>
   <energy>
    <i name="e_fr_energy">   -343.11049191 </i>
    <i name="e_wo_entrp">   -341.72618838 </i>
    <i name="e_0_energy">   -342.41834014 </i>
   </energy>
  </scstep>
  <scstep>
   <time name="dav">    2.68    2.69</time>
   <time name="total">    2.79    2.80</time>
   <energy>
    <i name="e_fr_energy">   -343.03315117 </i>
    <i name="e_wo_entrp">   -341.64774256 </i>
    <i name="e_0_energy">   -342.34044687 </i>
   </energy>
  </scstep>
  <scstep>
   <time name="dav">    2.65    2.65</time>
   <time name="total">    2.75    2.76</time>
   <energy>
    <i name="e_fr_energy">   -343.00210845 </i>
    <i name="e_wo_entrp">   -341.62520017 </i>
    <i name="e_0_energy">   -342.31365431 </i>
   </energy>
  </scstep>
  <scstep>
   <time name="dav">    2.65    2.65</time>
   <time name="total">    2.75    2.76</time>
   <energy>
    <i name="e_fr_energy">   -342.98004045 </i>
    <i name="e_wo_entrp">   -341.59220171 </i>
    <i name="e_0_energy">   -342.28612108 </i>
   </energy>
  </scstep>
  <scstep>
   <time name="dav">    2.62    2.62</time>
   <time name="total">    2.73    2.73</time>
   <energy>
    <i name="e_fr_energy">   -343.00996636 </i>
    <i name="e_wo_entrp">   -341.60400225 </i>
    <i name="e_0_energy">   -342.30698431 </i>
   </energy>
  </scstep>
  <scstep>
   <time name="dav">    2.63    2.64</time>
   <time name="total">    2.74    2.75</time>
   <energy>
    <i name="e_fr_energy">   -342.96094963 </i>
    <i name="e_wo_entrp">   -341.56071846 </i>
    <i name="e_0_energy">   -342.26083405 </i>
   </energy>
  </scstep>
  <scstep>
   <time name="dav">    2.66    2.67</time>
   <time name="total">    2.77    2.78</time>
   <energy>
    <i name="e_fr_energy">   -342.94564394 </i>
    <i name="e_wo_entrp">   -341.53684692 </i>
    <i name="e_0_energy">   -342.24124543 </i>
   </energy>
  </scstep>
  <scstep>
   <time name="dav">    2.66    2.67</time>
   <time name="total">    2.77    2.78</time>
   <energy>
    <i name="e_fr_energy">   -342.94296121 </i>
    <i name="e_wo_entrp">   -341.53705604 </i>
    <i name="e_0_energy">   -342.24000862 </i>
   </energy>
  </scstep>
  <scstep>
   <time name="dav">    2.65    2.66</time>
   <time name="total">    2.76    2.77</time>
   <energy>
    <i name="e_fr_energy">   -342.92934816 </i>
    <i name="e_wo_entrp">   -341.53661511 </i>
    <i name="e_0_energy">   -342.23298163 </i>
   </energy>
  </scstep>
  <scstep>
   <time name="dav">    2.60    2.60</time>
   <time name="total">    2.71    2.71</time>
   <energy>
    <i name="e_fr_energy">   -342.93251513 </i>
    <i name="e_wo_entrp">   -341.53308118 </i>
    <i name="e_0_energy">   -342.23279815 </i>
   </energy>
  </scstep>
  <scstep>
   <time name="dav">    2.71    2.72</time>
   <time name="total">    2.82    2.83</time>
   <energy>
    <i name="e_fr_energy">   -342.92721400 </i>
    <i name="e_wo_entrp">   -341.53395915 </i>
    <i name="e_0_energy">   -342.23058657 </i>
   </energy>
  </scstep>
  <scstep>
   <time name="dav">    2.63    2.63</time>
   <time name="total">    2.74    2.75</time>
   <energy>
    <i name="e_fr_energy">   -342.92517052 </i>
    <i name="e_wo_entrp">   -341.53757135 </i>
    <i name="e_0_energy">   -342.23137094 </i>
   </energy>
  </scstep>
  <scstep>
   <time name="dav">    2.59    2.59</time>
   <time name="total">    2.70    2.70</time>
   <energy>
    <i name="e_fr_energy">   -342.92490157 </i>
    <i name="e_wo_entrp">   -341.53599758 </i>
    <i name="e_0_energy">   -342.23044958 </i>
   </energy>
  </scstep>
  <scstep>
   <time name="dav">    2.63    2.64</time>
   <time name="total">    2.74    2.75</time>
   <energy>
    <i name="e_fr_energy">   -342.92347075 </i>
    <i name="e_wo_entrp">   -341.54196778 </i>
    <i name="e_0_energy">   -342.23271926 </i>
   </energy>
  </scstep>
  <scstep>
   <time name="dav">    2.42    2.42</time>
   <time name="total">    2.53    2.53</time>
   <energy>
    <i name="e_fr_energy">   -342.92393673 </i>
    <i name="e_wo_entrp">   -341.54316365 </i>
    <i name="e_0_energy">   -342.23355019 </i>
   </energy>
  </scstep>
  <scstep>
   <time name="dav">    2.13    2.14</time>
   <time name="total">    2.24    2.25</time>
   <energy>
    <i name="e_fr_energy">   -342.92416274 </i>
    <i name="e_wo_entrp">   -341.54531352 </i>
    <i name="e_0_energy">   -342.23473813 </i>
   </energy>
  </scstep>
  <scstep>
   <time name="dav">    1.89    1.89</time>
   <time name="total">    2.00    2.00</time>
   <energy>
    <i name="e_fr_energy">   -342.92451071 </i>
    <i name="e_wo_entrp">   -341.54470645 </i>
    <i name="e_0_energy">   -342.23460858 </i>
   </energy>
  </scstep>
  <scstep>
   <time name="dav">    1.63    1.64</time>
   <time name="total">    1.75    1.75</time>
   <energy>
    <i name="e_fr_energy">   -342.92482040 </i>
    <i name="e_wo_entrp">   -341.54451707 </i>
    <i name="e_0_energy">   -342.23466873 </i>
   </energy>
  </scstep>
  <scstep>
   <time name="dav">    1.67    1.67</time>
   <time name="total">    1.78    1.78</time>
   <energy>
    <i name="e_fr_energy">   -342.92556708 </i>
    <i name="e_wo_entrp">   -341.54546385 </i>
    <i name="e_0_energy">   -342.23551547 </i>
   </energy>
  </scstep>
  <scstep>
   <time name="dav">    1.73    1.73</time>
   <time name="total">    1.84    1.85</time>
   <energy>
    <i name="e_fr_energy">   -342.92596959 </i>
    <i name="e_wo_entrp">   -341.54537988 </i>
    <i name="e_0_energy">   -342.23567473 </i>
   </energy>
  </scstep>
  <scstep>
   <time name="dav">    1.55    1.55</time>
   <time name="total">    1.66    1.66</time>
   <energy>
    <i name="e_fr_energy">   -342.92627679 </i>
    <i name="e_wo_entrp">   -341.54495533 </i>
    <i name="e_0_energy">   -342.23561606 </i>
   </energy>
  </scstep>
  <scstep>
   <time name="dav">    1.58    1.58</time>
   <time name="total">    1.69    1.69</time>
   <energy>
    <i name="e_fr_energy">   -342.92666137 </i>
    <i name="e_wo_entrp">   -341.54469211 </i>
    <i name="e_0_energy">   -342.23567674 </i>
   </energy>
  </scstep>
  <scstep>
   <time name="dav">    1.52    1.53</time>
   <time name="total">    1.64    1.64</time>
   <energy>
    <i name="e_fr_energy">   -342.92690259 </i>
    <i name="e_wo_entrp">   -341.54445146 </i>
    <i name="e_0_energy">   -342.23567703 </i>
   </energy>
  </scstep>
  <scstep>
   <time name="dav">    1.62    1.62</time>
   <time name="total">    1.73    1.73</time>
   <energy>
    <i name="e_fr_energy">   -342.92738558 </i>
    <i name="e_wo_entrp">   -341.54518072 </i>
    <i name="e_0_energy">   -342.23628315 </i>
   </energy>
  </scstep>
  <scstep>
   <time name="dav">    1.53    1.53</time>
   <time name="total">    1.64    1.64</time>
   <energy>
    <i name="e_fr_energy">   -342.92759949 </i>
    <i name="e_wo_entrp">   -341.54528687 </i>
    <i name="e_0_energy">   -342.23644318 </i>
   </energy>
  </scstep>
  <scstep>
   <time name="dav">    1.61    1.62</time>
   <time name="total">    1.73    1.73</time>
   <energy>
    <i name="e_fr_energy">   -342.92804693 </i>
    <i name="e_wo_entrp">   -341.54577517 </i>
    <i name="e_0_energy">   -342.23691105 </i>
   </energy>
  </scstep>
  <scstep>
   <time name="dav">    1.54    1.54</time>
   <time name="total">    1.60    1.60</time>
   <energy>
    <i name="alphaZ">   1422.52235994 </i>
    <i name="ewald"> 102521.60681565 </i>
    <i name="hartreedc">-222733.70288808 </i>
    <i name="XCdc">   3610.22211246 </i>
    <i name="pawpsdc"> 128468.42859090 </i>
    <i name="pawaedc">-133436.23048657 </i>
    <i name="eentropy">     -1.38218363 </i>
    <i name="bandstr"> -16196.99748066 </i>
    <i name="atom"> 136002.60505376 </i>
    <i name="e_fr_energy">   -342.92810623 </i>
    <i name="e_wo_entrp">   -341.54592260 </i>
    <i name="e_0_energy">   -342.23701441 </i>
   </energy>
  </scstep>
  <structure>
   <crystal>
    <varray name="basis" >
     <v>      16.88469405       0.00000000       0.00000000 </v>
     <v>       0.00000000       9.57841000       0.00000000 </v>
     <v>       0.00000000       0.00000000      16.16908712 </v>
    </varray>
    <i name="volume">   2615.00256803 </i>
    <varray name="rec_basis" >
     <v>       0.05922524       0.00000000       0.00000000 </v>
     <v>       0.00000000       0.10440146       0.00000000 </v>
     <v>       0.00000000       0.00000000       0.06184641 </v>
    </varray>
   </crystal>
   <varray name="positions" >
    <v>       0.78004631       0.14529695       0.12058499 </v>
    <v>       0.26276233       0.64529695       0.02520102 </v>
    <v>       0.29733029       0.64529695       0.21596897 </v>
    <v>       0.43519032       0.14529695       0.05699568 </v>
    <v>       0.46975828       0.14529695       0.24776362 </v>
    <v>       0.95247430       0.64529695       0.15237965 </v>
    <v>       0.98704226       0.64529695       0.34314760 </v>
    <v>       0.12490229       0.14529695       0.18417431 </v>
    <v>       0.15947025       0.14529695       0.37494226 </v>
    <v>       0.60761831       0.64529695       0.08879033 </v>
    <v>       0.64218627       0.64529695       0.27955828 </v>
    <v>       0.90758278       0.01319395       0.09538397 </v>
    <v>       0.94215073       0.01319395       0.28615192 </v>
    <v>       0.39029880       0.51319395       0.00000000 </v>
    <v>       0.42486675       0.51319395       0.19076795 </v>
    <v>       0.45943471       0.51319395       0.38153589 </v>
    <v>       0.56272679       0.01319395       0.03179466 </v>
    <v>       0.59729475       0.01319395       0.22256261 </v>
    <v>       0.08001077       0.51319395       0.12717863 </v>
    <v>       0.11457873       0.51319395       0.31794658 </v>
    <v>       0.25243876       0.01319395       0.15897329 </v>
    <v>       0.28700672       0.01319395       0.34974124 </v>
    <v>       0.73515478       0.51319395       0.06358932 </v>
    <v>       0.76972274       0.51319395       0.25435726 </v>
    <v>       0.90758278       0.27739995       0.09538397 </v>
    <v>       0.94215073       0.27739995       0.28615192 </v>
    <v>       0.39029880       0.77739995       0.00000000 </v>
    <v>       0.42486675       0.77739995       0.19076795 </v>
    <v>       0.45943471       0.77739995       0.38153589 </v>
    <v>       0.56272679       0.27739995       0.03179466 </v>
    <v>       0.59729475       0.27739995       0.22256261 </v>
    <v>       0.08001077       0.77739995       0.12717863 </v>
    <v>       0.11457873       0.77739995       0.31794658 </v>
    <v>       0.25243876       0.27739995       0.15897329 </v>
    <v>       0.73515478       0.77739995       0.06358932 </v>
    <v>       0.76972274       0.77739995       0.25435726 </v>
    <v>       0.02602916       0.14529695       0.37317765 </v>
    <v>       0.99146121       0.14529695       0.18240970 </v>
    <v>       0.47417723       0.64529695       0.08702573 </v>
    <v>       0.50874518       0.64529695       0.27779368 </v>
    <v>       0.64660522       0.14529695       0.11882039 </v>
    <v>       0.68117318       0.14529695       0.30958834 </v>
    <v>       0.12932124       0.64529695       0.02343641 </v>
    <v>       0.16388920       0.64529695       0.21420436 </v>
    <v>       0.30174923       0.14529695       0.05523107 </v>
    <v>       0.33631719       0.14529695       0.24599902 </v>
    <v>       0.81903321       0.64529695       0.15061505 </v>
    <v>       0.85360117       0.64529695       0.34138299 </v>
    <v>       0.79449310       0.31351195       0.02373179 </v>
    <v>       0.82906105       0.31351195       0.21449973 </v>
    <v>       0.31177708       0.81351195       0.11911576 </v>
    <v>       0.34634503       0.81351195       0.30988371 </v>
    <v>       0.48420507       0.31351195       0.15091042 </v>
    <v>       0.51877303       0.31351195       0.34167837 </v>
    <v>       0.00148905       0.81351195       0.24629439 </v>
    <v>       0.96692109       0.81351195       0.05552644 </v>
    <v>       0.13934908       0.31351195       0.08732110 </v>
    <v>       0.17391704       0.31351195       0.27808905 </v>
    <v>       0.65663306       0.81351195       0.18270508 </v>
    <v>       0.69120102       0.81351195       0.37347302 </v>
    <v>       0.31177708       0.47708195       0.11911576 </v>
    <v>       0.34634503       0.47708195       0.30988371 </v>
    <v>       0.79449310       0.97708195       0.02373179 </v>
    <v>       0.82906105       0.97708195       0.21449973 </v>
    <v>       0.00148905       0.47708195       0.24629439 </v>
    <v>       0.96692109       0.47708195       0.05552644 </v>
    <v>       0.48420507       0.97708195       0.15091042 </v>
    <v>       0.51877303       0.97708195       0.34167837 </v>
    <v>       0.65663306       0.47708195       0.18270508 </v>
    <v>       0.69120102       0.47708195       0.37347302 </v>
    <v>       0.13934908       0.97708195       0.08732110 </v>
    <v>       0.17391704       0.97708195       0.27808905 </v>
   </varray>
  </structure>
  <varray name="forces" >
   <v>       0.43079912       0.01034824      -0.15702398 </v>
   <v>      -0.30360039       0.00158274       1.14752269 </v>
   <v>      -0.03100765      -0.05303186       0.36603303 </v>
   <v>      -0.36213957       0.00251473       0.82949999 </v>
   <v>      -0.33581372      -0.01307443       0.18012409 </v>
   <v>      -0.18331715       0.01673863      -0.02563195 </v>
   <v>      -0.82728420       0.02058536      -1.71108480 </v>
   <v>      -0.16462741       0.18474353      -0.16737638 </v>
   <v>      -0.74816221       0.03775539      -1.83866645 </v>
   <v>       0.08737328      -0.00102165       0.83494449 </v>
   <v>       0.05746762       0.01120028       0.58017403 </v>
   <v>      -0.32718756      -0.85020139       0.48570372 </v>
   <v>       0.47778927       0.48967897      -0.67683337 </v>
   <v>       0.00130406       0.63649258       1.71703726 </v>
   <v>      -0.23711809      -0.13911194       0.26951177 </v>
   <v>      -0.37430931      -0.37969307      -2.12255841 </v>
   <v>      -0.25698621       0.53143066       1.59547641 </v>
   <v>       0.13034415       0.17167531       0.37716204 </v>
   <v>       0.20857376      -0.43579757      -0.28998751 </v>
   <v>      -0.07957431      -0.22426684      -1.45131324 </v>
   <v>       0.25537659      -0.08407778      -0.21362203 </v>
   <v>      -0.11634716      -0.26526285      -1.91856580 </v>
   <v>       0.22622728      -0.36602373       0.93233378 </v>
   <v>       0.35751321      -0.19006344       0.35777653 </v>
   <v>      -0.34400525       0.83262609       0.48651279 </v>
   <v>       0.45471562      -0.48761013      -0.65463261 </v>
   <v>       0.01864967      -0.65525746       1.71764786 </v>
   <v>      -0.07901857       0.20939283       0.07294284 </v>
   <v>      -0.23551321       0.39360910      -2.00571635 </v>
   <v>      -0.25949610      -0.52339103       1.59766375 </v>
   <v>       0.09743869      -0.18056492       0.38153456 </v>
   <v>       0.23331072       0.42779224      -0.29565197 </v>
   <v>      -0.09913924       0.15300030      -1.37922452 </v>
   <v>       0.11153298       0.10812291      -0.02947548 </v>
   <v>       0.23779496       0.36817242       0.93405584 </v>
   <v>       0.35389719       0.20644122       0.35861996 </v>
   <v>      -1.10838276       0.04469023      -0.10445701 </v>
   <v>      -0.48705912      -0.00079632      -0.80267810 </v>
   <v>       0.30381536       0.01761649      -1.48518018 </v>
   <v>      -0.10573883       0.02362030       1.18280261 </v>
   <v>      -0.44720767      -0.00336985      -0.89230058 </v>
   <v>      -0.77126536       0.00069270      -0.58553603 </v>
   <v>       1.26215346      -0.00295959       0.15743625 </v>
   <v>       0.10047090       0.00030177       1.11280815 </v>
   <v>       1.28668397       0.06182707      -0.02545945 </v>
   <v>      -0.26114428      -0.30787737       0.85878065 </v>
   <v>      -0.50231678      -0.00292352      -0.69745684 </v>
   <v>      -0.13894947      -0.01571153       0.16069411 </v>
   <v>       0.05640703       0.56517805       0.40890022 </v>
   <v>       0.37679114      -0.45307179       0.76120690 </v>
   <v>      -0.10427701      -0.20507190      -1.15093554 </v>
   <v>       0.39710507       0.21379251       0.93092696 </v>
   <v>       0.06254192      -0.27851182      -0.89909019 </v>
   <v>      -0.01767106      -0.22402058      -0.02129844 </v>
   <v>       0.00251817      -0.22729428       0.97494448 </v>
   <v>      -0.03908117       0.58768503       0.47087984 </v>
   <v>      -0.03480474       0.02209221       0.47359538 </v>
   <v>      -0.17199499      -0.37686875       0.77283774 </v>
   <v>       0.04616201      -0.45470722      -0.67730174 </v>
   <v>       0.25946003      -0.84931556      -1.36526090 </v>
   <v>      -0.14328317       0.21413558      -1.08327349 </v>
   <v>       0.79142471       0.28631181      -0.10250141 </v>
   <v>       0.04181223      -0.57346521       0.40864360 </v>
   <v>       0.37378048       0.43886082       0.77013179 </v>
   <v>       0.03613027       0.22497622       0.97609793 </v>
   <v>      -0.02409380      -0.58275765       0.48401712 </v>
   <v>       0.00353794       0.24895773      -0.89919222 </v>
   <v>       0.05285131       0.21354198       0.01011810 </v>
   <v>       0.04548646       0.45496787      -0.66771166 </v>
   <v>       0.27675946       0.83220758      -1.38100292 </v>
   <v>      -0.03622797      -0.00819978       0.61938209 </v>
   <v>       0.24214540       0.15001336       1.02152019 </v>
  </varray>
  <varray name="stress" >
   <v>     -26.69379164       0.14626468      -6.52130296 </v>
   <v>       0.14626470     -27.20840705      -0.15141432 </v>
   <v>      -6.52130309      -0.15141413     -38.92101932 </v>
  </varray>
  <energy>
   <i name="e_fr_energy">   -342.92810623 </i>
   <i name="e_wo_entrp">   -341.54592260 </i>
   <i name="e_0_energy">   -342.23701441 </i>
  </energy>
  <time name="totalsc">  118.62  118.99</time>
  <eigenvalues>
   <array>
    <dimension dim="1">band</dimension>
    <dimension dim="2">kpoint</dimension>
    <dimension dim="3">spin</dimension>
    <field>eigene</field>
    <field>occ</field>
    <set>
     <set comment="spin 1">
      <set comment="kpoint 1">
       <r>  -64.4373    1.0000 </r>
       <r>  -64.4294    1.0000 </r>
       <r>  -64.4258    1.0000 </r>
       <r>  -64.4195    1.0000 </r>
       <r>  -64.4129    1.0000 </r>
       <r>  -64.4127    1.0000 </r>
       <r>  -64.3934    1.0000 </r>
       <r>  -64.3907    1.0000 </r>
       <r>  -64.3883    1.0000 </r>
       <r>  -64.3797    1.0000 </r>
       <r>  -64.3689    1.0000 </r>
       <r>  -64.3688    1.0000 </r>
       <r>  -64.3662    1.0000 </r>
       <r>  -64.3645    1.0000 </r>
       <r>  -64.3576    1.0000 </r>
       <r>  -64.3567    1.0000 </r>
       <r>  -64.3531    1.0000 </r>
       <r>  -64.3505    1.0000 </r>
       <r>  -64.3454    1.0000 </r>
       <r>  -64.3438    1.0000 </r>
       <r>  -64.3315    1.0000 </r>
       <r>  -64.3311    1.0000 </r>
       <r>  -64.3226    1.0000 </r>
       <r>  -64.3110    1.0000 </r>
       <r>  -64.3092    1.0000 </r>
       <r>  -64.3090    1.0000 </r>
       <r>  -64.3067    1.0000 </r>
       <r>  -64.3042    1.0000 </r>
       <r>  -64.2974    1.0000 </r>
       <r>  -64.2878    1.0000 </r>
       <r>  -64.2849    1.0000 </r>
       <r>  -64.2610    1.0000 </r>
       <r>  -64.2582    1.0000 </r>
       <r>  -64.2564    1.0000 </r>
       <r>  -64.2563    1.0000 </r>
       <r>  -64.2421    1.0000 </r>
       <r>  -64.2219    1.0000 </r>
       <r>  -64.2088    1.0000 </r>
       <r>  -64.2025    1.0000 </r>
       <r>  -64.1842    1.0000 </r>
       <r>  -64.1712    1.0000 </r>
       <r>  -64.1505    1.0000 </r>
       <r>  -64.1487    1.0000 </r>
       <r>  -64.1398    1.0000 </r>
       <r>  -64.1207    1.0000 </r>
       <r>  -64.1161    1.0000 </r>
       <r>  -64.1037    1.0000 </r>
       <r>  -64.0956    1.0000 </r>
       <r>  -64.0937    1.0000 </r>
       <r>  -64.0900    1.0000 </r>
       <r>  -64.0879    1.0000 </r>
       <r>  -64.0710    1.0000 </r>
       <r>  -64.0650    1.0000 </r>
       <r>  -64.0573    1.0000 </r>
       <r>  -63.9147    1.0000 </r>
       <r>  -63.9026    1.0000 </r>
       <r>  -63.8639    1.0000 </r>
       <r>  -63.8580    1.0000 </r>
       <r>  -63.8560    1.0000 </r>
       <r>  -63.8431    1.0000 </r>
       <r>  -63.8308    1.0000 </r>
       <r>  -63.8271    1.0000 </r>
       <r>  -63.7928    1.0000 </r>
       <r>  -63.7602    1.0000 </r>
       <r>  -63.7532    1.0000 </r>
       <r>  -63.7524    1.0000 </r>
       <r>  -63.7432    1.0000 </r>
       <r>  -63.7270    1.0000 </r>
       <r>  -63.7217    1.0000 </r>
       <r>  -63.6901    1.0000 </r>
       <r>  -63.6826    1.0000 </r>
       <r>  -63.6703    1.0000 </r>
       <r>  -63.6604    1.0000 </r>
       <r>  -63.6545    1.0000 </r>
       <r>  -63.6489    1.0000 </r>
       <r>  -63.6278    1.0000 </r>
       <r>  -63.6265    1.0000 </r>
       <r>  -63.6178    1.0000 </r>
       <r>  -63.5979    1.0000 </r>
       <r>  -63.5662    1.0000 </r>
       <r>  -63.5589    1.0000 </r>
       <r>  -63.5587    1.0000 </r>
       <r>  -63.5195    1.0000 </r>
       <r>  -63.5145    1.0000 </r>
       <r>  -63.5045    1.0000 </r>
       <r>  -63.4792    1.0000 </r>
       <r>  -63.4458    1.0000 </r>
       <r>  -63.4335    1.0000 </r>
       <r>  -63.4237    1.0000 </r>
       <r>  -63.4178    1.0000 </r>
       <r>  -63.3872    1.0000 </r>
       <r>  -63.3089    1.0000 </r>
       <r>  -63.3028    1.0000 </r>
       <r>  -63.3001    1.0000 </r>
       <r>  -63.2926    1.0000 </r>
       <r>  -63.2808    1.0000 </r>
       <r>  -63.1826    1.0000 </r>
       <r>  -63.1766    1.0000 </r>
       <r>  -63.1662    1.0000 </r>
       <r>  -63.1637    1.0000 </r>
       <r>  -63.1012    1.0000 </r>
       <r>  -63.0663    1.0000 </r>
       <r>  -63.0653    1.0000 </r>
       <r>  -63.0426    1.0000 </r>
       <r>  -63.0315    1.0000 </r>
       <r>  -63.0192    1.0000 </r>
       <r>  -63.0140    1.0000 </r>
       <r>  -62.9901    1.0000 </r>
       <r>  -15.2245    1.0000 </r>
       <r>  -14.9695    1.0000 </r>
       <r>  -14.8716    1.0000 </r>
       <r>  -14.5222    1.0000 </r>
       <r>  -14.3742    1.0000 </r>
       <r>  -14.3013    1.0000 </r>
       <r>  -14.2344    1.0000 </r>
       <r>  -14.2080    1.0000 </r>
       <r>  -14.0562    1.0000 </r>
       <r>  -14.0313    1.0000 </r>
       <r>  -13.9978    1.0000 </r>
       <r>  -13.9011    1.0000 </r>
       <r>  -13.8324    1.0000 </r>
       <r>  -13.7532    1.0000 </r>
       <r>  -13.6987    1.0000 </r>
       <r>  -13.5856    1.0000 </r>
       <r>  -13.5076    1.0000 </r>
       <r>  -13.4399    1.0000 </r>
       <r>  -13.3292    1.0000 </r>
       <r>  -13.2949    1.0000 </r>
       <r>  -13.2229    1.0000 </r>
       <r>  -13.0881    1.0000 </r>
       <r>  -13.0219    1.0000 </r>
       <r>  -12.9237    1.0000 </r>
       <r>  -12.9023    1.0000 </r>
       <r>  -12.7835    1.0000 </r>
       <r>  -12.7479    1.0000 </r>
       <r>  -12.6763    1.0000 </r>
       <r>  -12.6533    1.0000 </r>
       <r>  -12.5890    1.0000 </r>
       <r>  -12.4690    1.0000 </r>
       <r>  -12.4256    1.0000 </r>
       <r>  -12.3747    1.0000 </r>
       <r>  -12.1747    1.0000 </r>
       <r>  -11.9630    1.0000 </r>
       <r>  -11.8304    1.0000 </r>
       <r>   -7.0069    1.0000 </r>
       <r>   -6.9629    1.0000 </r>
       <r>   -6.8846    1.0000 </r>
       <r>   -6.8473    1.0000 </r>
       <r>   -6.7611    1.0000 </r>
       <r>   -6.5886    1.0000 </r>
       <r>   -6.4727    1.0000 </r>
       <r>   -6.4349    1.0000 </r>
       <r>   -6.3899    1.0000 </r>
       <r>   -6.3532    1.0000 </r>
       <r>   -6.2996    1.0000 </r>
       <r>   -6.2698    1.0000 </r>
       <r>   -6.2056    1.0000 </r>
       <r>   -6.1034    1.0000 </r>
       <r>   -6.0539    1.0000 </r>
       <r>   -6.0347    1.0000 </r>
       <r>   -6.0290    1.0000 </r>
       <r>   -5.9815    1.0000 </r>
       <r>   -5.9258    1.0000 </r>
       <r>   -5.8578    1.0000 </r>
       <r>   -5.8281    1.0000 </r>
       <r>   -5.7905    1.0000 </r>
       <r>   -5.7527    1.0000 </r>
       <r>   -5.7063    1.0000 </r>
       <r>   -5.6382    1.0000 </r>
       <r>   -5.6093    1.0000 </r>
       <r>   -5.6018    1.0000 </r>
       <r>   -5.4905    1.0000 </r>
       <r>   -5.4552    1.0000 </r>
       <r>   -5.4268    1.0000 </r>
       <r>   -5.3902    1.0000 </r>
       <r>   -5.3417    1.0000 </r>
       <r>   -5.3081    1.0000 </r>
       <r>   -5.2893    1.0000 </r>
       <r>   -5.2324    1.0000 </r>
       <r>   -5.2123    1.0000 </r>
       <r>   -5.1864    1.0000 </r>
       <r>   -5.1597    1.0000 </r>
       <r>   -5.1000    1.0000 </r>
       <r>   -5.0222    1.0000 </r>
       <r>   -4.9793    1.0000 </r>
       <r>   -4.9372    1.0000 </r>
       <r>   -4.8779    1.0000 </r>
       <r>   -4.8255    1.0000 </r>
       <r>   -4.7872    1.0000 </r>
       <r>   -4.7408    1.0000 </r>
       <r>   -4.7170    1.0000 </r>
       <r>   -4.6564    1.0000 </r>
       <r>   -4.6208    1.0000 </r>
       <r>   -4.5852    1.0000 </r>
       <r>   -4.5303    1.0000 </r>
       <r>   -4.5154    1.0000 </r>
       <r>   -4.4931    1.0000 </r>
       <r>   -4.4655    1.0000 </r>
       <r>   -4.4317    1.0000 </r>
       <r>   -4.4247    1.0000 </r>
       <r>   -4.3932    1.0000 </r>
       <r>   -4.3388    1.0000 </r>
       <r>   -4.3234    1.0000 </r>
       <r>   -4.2946    1.0000 </r>
       <r>   -4.2412    1.0000 </r>
       <r>   -4.1396    1.0000 </r>
       <r>   -4.1217    1.0000 </r>
       <r>   -4.0787    1.0000 </r>
       <r>   -4.0445    1.0000 </r>
       <r>   -4.0365    1.0000 </r>
       <r>   -4.0259    1.0000 </r>
       <r>   -3.9825    1.0000 </r>
       <r>   -3.9418    1.0000 </r>
       <r>   -3.9288    1.0000 </r>
       <r>   -3.9073    1.0000 </r>
       <r>   -3.8943    1.0000 </r>
       <r>   -3.8649    1.0000 </r>
       <r>   -3.8321    1.0000 </r>
       <r>   -3.7455    1.0000 </r>
       <r>   -3.7338    1.0000 </r>
       <r>   -3.6970    1.0000 </r>
       <r>   -3.6696    1.0000 </r>
       <r>   -3.6609    1.0000 </r>
       <r>   -3.6522    1.0000 </r>
       <r>   -3.6215    1.0000 </r>
       <r>   -3.6020    1.0000 </r>
       <r>   -3.5446    1.0000 </r>
       <r>   -3.4593    1.0000 </r>
       <r>   -3.4455    1.0000 </r>
       <r>   -3.4085    1.0000 </r>
       <r>   -3.3855    1.0000 </r>
       <r>   -3.3055    1.0000 </r>
       <r>   -3.2790    1.0000 </r>
       <r>   -3.2543    1.0000 </r>
       <r>   -3.2432    1.0000 </r>
       <r>   -3.2131    1.0000 </r>
       <r>   -3.1798    1.0000 </r>
       <r>   -3.1636    1.0000 </r>
       <r>   -3.1246    1.0000 </r>
       <r>   -3.0909    1.0000 </r>
       <r>   -3.0454    1.0000 </r>
       <r>   -2.9993    1.0000 </r>
       <r>   -2.9743    1.0000 </r>
       <r>   -2.9362    1.0000 </r>
       <r>   -2.9096    1.0000 </r>
       <r>   -2.8658    1.0000 </r>
       <r>   -2.8449    1.0000 </r>
       <r>   -2.7919    1.0000 </r>
       <r>   -2.7779    1.0000 </r>
       <r>   -2.7632    1.0000 </r>
       <r>   -2.7073    1.0000 </r>
       <r>   -2.6884    1.0000 </r>
       <r>   -2.6319    1.0000 </r>
       <r>   -2.6070    1.0000 </r>
       <r>   -2.5825    1.0000 </r>
       <r>   -2.5661    1.0000 </r>
       <r>   -2.5419    1.0000 </r>
       <r>   -2.5197    1.0000 </r>
       <r>   -2.4855    1.0000 </r>
       <r>   -2.4674    1.0000 </r>
       <r>   -2.4480    1.0000 </r>
       <r>   -2.4272    1.0000 </r>
       <r>   -2.4018    1.0000 </r>
       <r>   -2.3922    1.0000 </r>
       <r>   -2.3709    1.0000 </r>
       <r>   -2.3505    1.0000 </r>
       <r>   -2.3419    1.0000 </r>
       <r>   -2.3297    1.0000 </r>
       <r>   -2.3284    1.0000 </r>
       <r>   -2.2853    1.0000 </r>
       <r>   -2.2688    1.0000 </r>
       <r>   -2.2646    1.0000 </r>
       <r>   -2.2583    1.0000 </r>
       <r>   -2.2160    1.0000 </r>
       <r>   -2.2061    1.0000 </r>
       <r>   -2.1949    1.0000 </r>
       <r>   -2.1829    1.0000 </r>
       <r>   -2.1781    1.0000 </r>
       <r>   -2.1716    1.0000 </r>
       <r>   -2.1525    1.0000 </r>
       <r>   -2.1366    1.0000 </r>
       <r>   -2.1219    1.0000 </r>
       <r>   -2.0762    1.0000 </r>
       <r>   -2.0641    1.0000 </r>
       <r>   -2.0557    1.0000 </r>
       <r>   -2.0441    1.0000 </r>
       <r>   -2.0301    1.0000 </r>
       <r>   -2.0149    1.0000 </r>
       <r>   -1.9987    1.0000 </r>
       <r>   -1.9814    1.0000 </r>
       <r>   -1.9698    1.0000 </r>
       <r>   -1.9619    1.0000 </r>
       <r>   -1.9534    1.0000 </r>
       <r>   -1.9403    1.0000 </r>
       <r>   -1.9275    1.0000 </r>
       <r>   -1.9228    1.0000 </r>
       <r>   -1.9172    1.0000 </r>
       <r>   -1.9045    1.0000 </r>
       <r>   -1.8974    1.0000 </r>
       <r>   -1.8906    1.0000 </r>
       <r>   -1.8741    1.0000 </r>
       <r>   -1.8715    1.0000 </r>
       <r>   -1.8654    1.0000 </r>
       <r>   -1.8586    1.0000 </r>
       <r>   -1.8445    1.0000 </r>
       <r>   -1.8375    1.0000 </r>
       <r>   -1.8288    1.0000 </r>
       <r>   -1.8025    1.0000 </r>
       <r>   -1.7868    1.0000 </r>
       <r>   -1.7852    1.0000 </r>
       <r>   -1.7843    1.0000 </r>
       <r>   -1.7624    1.0000 </r>
       <r>   -1.7494    1.0000 </r>
       <r>   -1.7391    1.0000 </r>
       <r>   -1.7154    1.0000 </r>
       <r>   -1.7023    1.0000 </r>
       <r>   -1.6982    1.0000 </r>
       <r>   -1.6793    1.0000 </r>
       <r>   -1.6729    1.0000 </r>
       <r>   -1.6437    1.0000 </r>
       <r>   -1.6341    1.0000 </r>
       <r>   -1.6206    1.0000 </r>
       <r>   -1.6083    1.0000 </r>
       <r>   -1.5953    1.0000 </r>
       <r>   -1.5825    1.0000 </r>
       <r>   -1.5800    1.0000 </r>
       <r>   -1.5680    1.0000 </r>
       <r>   -1.5585    1.0000 </r>
       <r>   -1.5392    1.0000 </r>
       <r>   -1.5260    1.0000 </r>
       <r>   -1.5171    1.0000 </r>
       <r>   -1.5099    1.0000 </r>
       <r>   -1.5038    1.0000 </r>
       <r>   -1.4891    1.0000 </r>
       <r>   -1.4764    1.0000 </r>
       <r>   -1.4591    1.0000 </r>
       <r>   -1.4582    1.0000 </r>
       <r>   -1.4457    1.0000 </r>
       <r>   -1.4220    1.0000 </r>
       <r>   -1.3992    1.0000 </r>
       <r>   -1.3742    1.0000 </r>
       <r>   -1.3723    1.0000 </r>
       <r>   -1.3657    1.0000 </r>
       <r>   -1.3339    1.0000 </r>
       <r>   -1.3279    1.0000 </r>
       <r>   -1.3198    1.0000 </r>
       <r>   -1.3001    1.0000 </r>
       <r>   -1.2650    1.0000 </r>
       <r>   -1.2441    1.0000 </r>
       <r>   -1.2250    1.0000 </r>
       <r>   -1.2205    1.0000 </r>
       <r>   -1.1988    1.0000 </r>
       <r>   -1.1885    1.0000 </r>
       <r>   -1.1681    1.0000 </r>
       <r>   -1.1476    1.0000 </r>
       <r>   -1.1376    1.0000 </r>
       <r>   -1.1273    1.0000 </r>
       <r>   -1.1082    1.0000 </r>
       <r>   -1.0931    1.0000 </r>
       <r>   -1.0885    1.0000 </r>
       <r>   -1.0376    1.0000 </r>
       <r>   -0.9952    1.0000 </r>
       <r>   -0.9872    1.0000 </r>
       <r>   -0.9791    1.0000 </r>
       <r>   -0.9743    1.0000 </r>
       <r>   -0.9537    1.0000 </r>
       <r>   -0.9511    1.0000 </r>
       <r>   -0.9348    1.0000 </r>
       <r>   -0.9240    1.0000 </r>
       <r>   -0.9154    1.0000 </r>
       <r>   -0.9094    1.0000 </r>
       <r>   -0.8939    1.0000 </r>
       <r>   -0.8657    1.0000 </r>
       <r>   -0.8451    0.9999 </r>
       <r>   -0.8121    0.9999 </r>
       <r>   -0.7907    0.9998 </r>
       <r>   -0.7625    0.9995 </r>
       <r>   -0.7530    0.9994 </r>
       <r>   -0.7357    0.9991 </r>
       <r>   -0.6924    0.9975 </r>
       <r>   -0.6815    0.9968 </r>
       <r>   -0.6633    0.9953 </r>
       <r>   -0.6418    0.9928 </r>
       <r>   -0.6291    0.9908 </r>
       <r>   -0.6052    0.9857 </r>
       <r>   -0.5788    0.9773 </r>
       <r>   -0.5535    0.9658 </r>
       <r>   -0.5393    0.9575 </r>
       <r>   -0.5033    0.9289 </r>
       <r>   -0.4916    0.9170 </r>
       <r>   -0.4635    0.8822 </r>
       <r>   -0.4256    0.8207 </r>
       <r>   -0.3945    0.7576 </r>
       <r>   -0.3757    0.7140 </r>
       <r>   -0.3470    0.6414 </r>
       <r>   -0.2976    0.5051 </r>
       <r>   -0.2893    0.4818 </r>
       <r>   -0.2677    0.4215 </r>
       <r>   -0.2373    0.3397 </r>
       <r>   -0.2016    0.2527 </r>
       <r>   -0.1416    0.1378 </r>
       <r>   -0.1198    0.1067 </r>
       <r>   -0.1059    0.0897 </r>
       <r>   -0.0597    0.0476 </r>
       <r>   -0.0432    0.0371 </r>
       <r>   -0.0269    0.0286 </r>
       <r>   -0.0106    0.0219 </r>
       <r>    0.0493    0.0073 </r>
       <r>    0.1010    0.0025 </r>
       <r>    0.1316    0.0013 </r>
       <r>    0.2573    0.0000 </r>
       <r>    0.2717    0.0000 </r>
       <r>    0.2978    0.0000 </r>
       <r>    0.3059    0.0000 </r>
       <r>    0.3334    0.0000 </r>
       <r>    0.3805    0.0000 </r>
       <r>    0.4214    0.0000 </r>
       <r>    0.4659    0.0000 </r>
       <r>    0.5303    0.0000 </r>
       <r>    0.5750    0.0000 </r>
       <r>    0.5909    0.0000 </r>
       <r>    0.6111    0.0000 </r>
       <r>    0.6472    0.0000 </r>
       <r>    0.7102    0.0000 </r>
       <r>    0.7331    0.0000 </r>
       <r>    0.7572    0.0000 </r>
       <r>    0.7746    0.0000 </r>
       <r>    0.7880    0.0000 </r>
       <r>    0.8692    0.0000 </r>
       <r>    0.8847    0.0000 </r>
       <r>    0.9030    0.0000 </r>
       <r>    0.9320    0.0000 </r>
       <r>    0.9488    0.0000 </r>
       <r>    0.9931    0.0000 </r>
       <r>    1.0334    0.0000 </r>
       <r>    1.1144    0.0000 </r>
       <r>    1.4398    0.0000 </r>
       <r>    1.5298    0.0000 </r>
       <r>    1.6935    0.0000 </r>
       <r>    2.4689    0.0000 </r>
       <r>    2.5999    0.0000 </r>
       <r>    2.7173    0.0000 </r>
       <r>    3.0742    0.0000 </r>
       <r>    3.2190    0.0000 </r>
       <r>    3.4330    0.0000 </r>
       <r>    3.6632    0.0000 </r>
       <r>    3.7200    0.0000 </r>
       <r>    3.9895    0.0000 </r>
       <r>    3.9938    0.0000 </r>
       <r>    4.0333    0.0000 </r>
       <r>    4.1178    0.0000 </r>
       <r>    4.1443    0.0000 </r>
       <r>    4.2122    0.0000 </r>
       <r>    4.3607    0.0000 </r>
       <r>    4.4102    0.0000 </r>
       <r>    4.4256    0.0000 </r>
       <r>    4.4679    0.0000 </r>
       <r>    4.4975    0.0000 </r>
       <r>    4.5524    0.0000 </r>
       <r>    4.6724    0.0000 </r>
       <r>    4.7165    0.0000 </r>
       <r>    4.7420    0.0000 </r>
       <r>    4.8079    0.0000 </r>
       <r>    4.8779    0.0000 </r>
       <r>    4.9391    0.0000 </r>
       <r>    5.0507    0.0000 </r>
       <r>    5.1367    0.0000 </r>
       <r>    5.1902    0.0000 </r>
       <r>    5.2786    0.0000 </r>
       <r>    5.2949    0.0000 </r>
       <r>    5.3436    0.0000 </r>
       <r>    5.3864    0.0000 </r>
       <r>    5.4418    0.0000 </r>
       <r>    5.4620    0.0000 </r>
       <r>    5.5158    0.0000 </r>
       <r>    5.5403    0.0000 </r>
       <r>    5.5660    0.0000 </r>
       <r>    5.6277    0.0000 </r>
       <r>    5.6557    0.0000 </r>
       <r>    5.7240    0.0000 </r>
      </set>
     </set>
    </set>
   </array>
  </eigenvalues>
  <separator name="orbital magnetization" >
   <v name="MAGDIPOLOUT">      0.00000000      0.00000000      0.00000000</v>
  </separator>
  <dos>
   <i name="efermi">     -0.29576178 </i>
   <total>
    <array>
     <dimension dim="1">gridpoints</dimension>
     <dimension dim="2">spin</dimension>
     <field>energy</field>
     <field>total</field>
     <field>integrated</field>
     <set>
      <set comment="spin 1">
       <r>   -67.9454     0.0000     0.0000 </r>
       <r>   -67.6882     0.0000     0.0000 </r>
       <r>   -67.4309     0.0000     0.0000 </r>
       <r>   -67.1736     0.0000     0.0000 </r>
       <r>   -66.9164     0.0000     0.0000 </r>
       <r>   -66.6591     0.0000     0.0000 </r>
       <r>   -66.4019     0.0000     0.0000 </r>
       <r>   -66.1446     0.0000     0.0000 </r>
       <r>   -65.8873     0.0000     0.0000 </r>
       <r>   -65.6301     0.0000     0.0000 </r>
       <r>   -65.3728     0.0000     0.0000 </r>
       <r>   -65.1156     0.0000     0.0000 </r>
       <r>   -64.8583     0.0844     0.0217 </r>
       <r>   -64.6011    12.2726     3.1790 </r>
       <r>   -64.3438   137.6055    38.5791 </r>
       <r>   -64.0865   207.0924    91.8554 </r>
       <r>   -63.8293   121.1633   123.0257 </r>
       <r>   -63.5720   133.0402   157.2514 </r>
       <r>   -63.3148   106.9554   184.7665 </r>
       <r>   -63.0575    79.0258   205.0966 </r>
       <r>   -62.8002    39.2299   215.1888 </r>
       <r>   -62.5430     3.1349   215.9953 </r>
       <r>   -62.2857     0.0183   216.0000 </r>
       <r>   -62.0285     0.0000   216.0000 </r>
       <r>   -61.7712     0.0000   216.0000 </r>
       <r>   -61.5140     0.0000   216.0000 </r>
       <r>   -61.2567     0.0000   216.0000 </r>
       <r>   -60.9994     0.0000   216.0000 </r>
       <r>   -60.7422     0.0000   216.0000 </r>
       <r>   -60.4849     0.0000   216.0000 </r>
       <r>   -60.2277     0.0000   216.0000 </r>
       <r>   -59.9704     0.0000   216.0000 </r>
       <r>   -59.7131     0.0000   216.0000 </r>
       <r>   -59.4559     0.0000   216.0000 </r>
       <r>   -59.1986     0.0000   216.0000 </r>
       <r>   -58.9414     0.0000   216.0000 </r>
       <r>   -58.6841     0.0000   216.0000 </r>
       <r>   -58.4269     0.0000   216.0000 </r>
       <r>   -58.1696     0.0000   216.0000 </r>
       <r>   -57.9123     0.0000   216.0000 </r>
       <r>   -57.6551     0.0000   216.0000 </r>
       <r>   -57.3978     0.0000   216.0000 </r>
       <r>   -57.1406     0.0000   216.0000 </r>
       <r>   -56.8833     0.0000   216.0000 </r>
       <r>   -56.6260     0.0000   216.0000 </r>
       <r>   -56.3688     0.0000   216.0000 </r>
       <r>   -56.1115     0.0000   216.0000 </r>
       <r>   -55.8543     0.0000   216.0000 </r>
       <r>   -55.5970     0.0000   216.0000 </r>
       <r>   -55.3398     0.0000   216.0000 </r>
       <r>   -55.0825     0.0000   216.0000 </r>
       <r>   -54.8252     0.0000   216.0000 </r>
       <r>   -54.5680     0.0000   216.0000 </r>
       <r>   -54.3107     0.0000   216.0000 </r>
       <r>   -54.0535     0.0000   216.0000 </r>
       <r>   -53.7962     0.0000   216.0000 </r>
       <r>   -53.5389     0.0000   216.0000 </r>
       <r>   -53.2817     0.0000   216.0000 </r>
       <r>   -53.0244     0.0000   216.0000 </r>
       <r>   -52.7672     0.0000   216.0000 </r>
       <r>   -52.5099     0.0000   216.0000 </r>
       <r>   -52.2527     0.0000   216.0000 </r>
       <r>   -51.9954     0.0000   216.0000 </r>
       <r>   -51.7381     0.0000   216.0000 </r>
       <r>   -51.4809     0.0000   216.0000 </r>
       <r>   -51.2236     0.0000   216.0000 </r>
       <r>   -50.9664     0.0000   216.0000 </r>
       <r>   -50.7091     0.0000   216.0000 </r>
       <r>   -50.4518     0.0000   216.0000 </r>
       <r>   -50.1946     0.0000   216.0000 </r>
       <r>   -49.9373     0.0000   216.0000 </r>
       <r>   -49.6801     0.0000   216.0000 </r>
       <r>   -49.4228     0.0000   216.0000 </r>
       <r>   -49.1655     0.0000   216.0000 </r>
       <r>   -48.9083     0.0000   216.0000 </r>
       <r>   -48.6510     0.0000   216.0000 </r>
       <r>   -48.3938     0.0000   216.0000 </r>
       <r>   -48.1365     0.0000   216.0000 </r>
       <r>   -47.8793     0.0000   216.0000 </r>
       <r>   -47.6220     0.0000   216.0000 </r>
       <r>   -47.3647     0.0000   216.0000 </r>
       <r>   -47.1075     0.0000   216.0000 </r>
       <r>   -46.8502     0.0000   216.0000 </r>
       <r>   -46.5930     0.0000   216.0000 </r>
       <r>   -46.3357     0.0000   216.0000 </r>
       <r>   -46.0784     0.0000   216.0000 </r>
       <r>   -45.8212     0.0000   216.0000 </r>
       <r>   -45.5639     0.0000   216.0000 </r>
       <r>   -45.3067     0.0000   216.0000 </r>
       <r>   -45.0494     0.0000   216.0000 </r>
       <r>   -44.7922     0.0000   216.0000 </r>
       <r>   -44.5349     0.0000   216.0000 </r>
       <r>   -44.2776     0.0000   216.0000 </r>
       <r>   -44.0204     0.0000   216.0000 </r>
       <r>   -43.7631     0.0000   216.0000 </r>
       <r>   -43.5059     0.0000   216.0000 </r>
       <r>   -43.2486     0.0000   216.0000 </r>
       <r>   -42.9913     0.0000   216.0000 </r>
       <r>   -42.7341     0.0000   216.0000 </r>
       <r>   -42.4768     0.0000   216.0000 </r>
       <r>   -42.2196     0.0000   216.0000 </r>
       <r>   -41.9623     0.0000   216.0000 </r>
       <r>   -41.7051     0.0000   216.0000 </r>
       <r>   -41.4478     0.0000   216.0000 </r>
       <r>   -41.1905     0.0000   216.0000 </r>
       <r>   -40.9333     0.0000   216.0000 </r>
       <r>   -40.6760     0.0000   216.0000 </r>
       <r>   -40.4188     0.0000   216.0000 </r>
       <r>   -40.1615     0.0000   216.0000 </r>
       <r>   -39.9042     0.0000   216.0000 </r>
       <r>   -39.6470     0.0000   216.0000 </r>
       <r>   -39.3897     0.0000   216.0000 </r>
       <r>   -39.1325     0.0000   216.0000 </r>
       <r>   -38.8752     0.0000   216.0000 </r>
       <r>   -38.6180     0.0000   216.0000 </r>
       <r>   -38.3607     0.0000   216.0000 </r>
       <r>   -38.1034     0.0000   216.0000 </r>
       <r>   -37.8462     0.0000   216.0000 </r>
       <r>   -37.5889     0.0000   216.0000 </r>
       <r>   -37.3317     0.0000   216.0000 </r>
       <r>   -37.0744     0.0000   216.0000 </r>
       <r>   -36.8171     0.0000   216.0000 </r>
       <r>   -36.5599     0.0000   216.0000 </r>
       <r>   -36.3026     0.0000   216.0000 </r>
       <r>   -36.0454     0.0000   216.0000 </r>
       <r>   -35.7881     0.0000   216.0000 </r>
       <r>   -35.5309     0.0000   216.0000 </r>
       <r>   -35.2736     0.0000   216.0000 </r>
       <r>   -35.0163     0.0000   216.0000 </r>
       <r>   -34.7591     0.0000   216.0000 </r>
       <r>   -34.5018     0.0000   216.0000 </r>
       <r>   -34.2446     0.0000   216.0000 </r>
       <r>   -33.9873     0.0000   216.0000 </r>
       <r>   -33.7300     0.0000   216.0000 </r>
       <r>   -33.4728     0.0000   216.0000 </r>
       <r>   -33.2155     0.0000   216.0000 </r>
       <r>   -32.9583     0.0000   216.0000 </r>
       <r>   -32.7010     0.0000   216.0000 </r>
       <r>   -32.4438     0.0000   216.0000 </r>
       <r>   -32.1865     0.0000   216.0000 </r>
       <r>   -31.9292     0.0000   216.0000 </r>
       <r>   -31.6720     0.0000   216.0000 </r>
       <r>   -31.4147     0.0000   216.0000 </r>
       <r>   -31.1575     0.0000   216.0000 </r>
       <r>   -30.9002     0.0000   216.0000 </r>
       <r>   -30.6429     0.0000   216.0000 </r>
       <r>   -30.3857     0.0000   216.0000 </r>
       <r>   -30.1284     0.0000   216.0000 </r>
       <r>   -29.8712     0.0000   216.0000 </r>
       <r>   -29.6139     0.0000   216.0000 </r>
       <r>   -29.3567     0.0000   216.0000 </r>
       <r>   -29.0994     0.0000   216.0000 </r>
       <r>   -28.8421     0.0000   216.0000 </r>
       <r>   -28.5849     0.0000   216.0000 </r>
       <r>   -28.3276     0.0000   216.0000 </r>
       <r>   -28.0704     0.0000   216.0000 </r>
       <r>   -27.8131     0.0000   216.0000 </r>
       <r>   -27.5558     0.0000   216.0000 </r>
       <r>   -27.2986     0.0000   216.0000 </r>
       <r>   -27.0413     0.0000   216.0000 </r>
       <r>   -26.7841     0.0000   216.0000 </r>
       <r>   -26.5268     0.0000   216.0000 </r>
       <r>   -26.2696     0.0000   216.0000 </r>
       <r>   -26.0123     0.0000   216.0000 </r>
       <r>   -25.7550     0.0000   216.0000 </r>
       <r>   -25.4978     0.0000   216.0000 </r>
       <r>   -25.2405     0.0000   216.0000 </r>
       <r>   -24.9833     0.0000   216.0000 </r>
       <r>   -24.7260     0.0000   216.0000 </r>
       <r>   -24.4687     0.0000   216.0000 </r>
       <r>   -24.2115     0.0000   216.0000 </r>
       <r>   -23.9542     0.0000   216.0000 </r>
       <r>   -23.6970     0.0000   216.0000 </r>
       <r>   -23.4397     0.0000   216.0000 </r>
       <r>   -23.1825     0.0000   216.0000 </r>
       <r>   -22.9252     0.0000   216.0000 </r>
       <r>   -22.6679     0.0000   216.0000 </r>
       <r>   -22.4107     0.0000   216.0000 </r>
       <r>   -22.1534     0.0000   216.0000 </r>
       <r>   -21.8962     0.0000   216.0000 </r>
       <r>   -21.6389     0.0000   216.0000 </r>
       <r>   -21.3816     0.0000   216.0000 </r>
       <r>   -21.1244     0.0000   216.0000 </r>
       <r>   -20.8671     0.0000   216.0000 </r>
       <r>   -20.6099     0.0000   216.0000 </r>
       <r>   -20.3526     0.0000   216.0000 </r>
       <r>   -20.0954     0.0000   216.0000 </r>
       <r>   -19.8381     0.0000   216.0000 </r>
       <r>   -19.5808     0.0000   216.0000 </r>
       <r>   -19.3236     0.0000   216.0000 </r>
       <r>   -19.0663     0.0000   216.0000 </r>
       <r>   -18.8091     0.0000   216.0000 </r>
       <r>   -18.5518     0.0000   216.0000 </r>
       <r>   -18.2945     0.0000   216.0000 </r>
       <r>   -18.0373     0.0000   216.0000 </r>
       <r>   -17.7800     0.0000   216.0000 </r>
       <r>   -17.5228     0.0000   216.0000 </r>
       <r>   -17.2655     0.0000   216.0000 </r>
       <r>   -17.0083     0.0000   216.0000 </r>
       <r>   -16.7510     0.0000   216.0000 </r>
       <r>   -16.4937     0.0000   216.0000 </r>
       <r>   -16.2365     0.0000   216.0000 </r>
       <r>   -15.9792     0.0000   216.0000 </r>
       <r>   -15.7220     0.0017   216.0004 </r>
       <r>   -15.4647     0.3479   216.0899 </r>
       <r>   -15.2074     4.3390   217.2062 </r>
       <r>   -14.9502     9.4491   219.6371 </r>
       <r>   -14.6929     9.1919   222.0017 </r>
       <r>   -14.4357    10.6389   224.7387 </r>
       <r>   -14.1784    23.8031   230.8623 </r>
       <r>   -13.9211    29.1009   238.3487 </r>
       <r>   -13.6639    27.0115   245.2976 </r>
       <r>   -13.4066    24.8405   251.6881 </r>
       <r>   -13.1494    24.8295   258.0757 </r>
       <r>   -12.8921    25.7054   264.6886 </r>
       <r>   -12.6349    31.1509   272.7024 </r>
       <r>   -12.3776    27.0140   279.6520 </r>
       <r>   -12.1203    14.9089   283.4875 </r>
       <r>   -11.8631    10.9700   286.3096 </r>
       <r>   -11.6058     6.0895   287.8762 </r>
       <r>   -11.3486     0.4788   287.9993 </r>
       <r>   -11.0913     0.0026   288.0000 </r>
       <r>   -10.8340     0.0000   288.0000 </r>
       <r>   -10.5768     0.0000   288.0000 </r>
       <r>   -10.3195     0.0000   288.0000 </r>
       <r>   -10.0623     0.0000   288.0000 </r>
       <r>    -9.8050     0.0000   288.0000 </r>
       <r>    -9.5478     0.0000   288.0000 </r>
       <r>    -9.2905     0.0000   288.0000 </r>
       <r>    -9.0332     0.0000   288.0000 </r>
       <r>    -8.7760     0.0000   288.0000 </r>
       <r>    -8.5187     0.0000   288.0000 </r>
       <r>    -8.2615     0.0000   288.0000 </r>
       <r>    -8.0042     0.0000   288.0000 </r>
       <r>    -7.7469     0.0000   288.0000 </r>
       <r>    -7.4897     0.0033   288.0009 </r>
       <r>    -7.2324     0.7304   288.1888 </r>
       <r>    -6.9752    11.4471   291.1336 </r>
       <r>    -6.7179    22.9636   297.0412 </r>
       <r>    -6.4607    23.5632   303.1030 </r>
       <r>    -6.2034    37.1110   312.6502 </r>
       <r>    -5.9461    42.9779   323.7066 </r>
       <r>    -5.6889    45.6809   335.4584 </r>
       <r>    -5.4316    45.5804   347.1843 </r>
       <r>    -5.1744    51.5271   360.4401 </r>
       <r>    -4.9171    43.9216   371.7393 </r>
       <r>    -4.6598    46.4125   383.6793 </r>
       <r>    -4.4026    59.2102   398.9116 </r>
       <r>    -4.1453    55.4370   413.1733 </r>
       <r>    -3.8881    64.1380   429.6733 </r>
       <r>    -3.6308    65.4899   446.5211 </r>
       <r>    -3.3736    56.8235   461.1394 </r>
       <r>    -3.1163    60.2181   476.6311 </r>
       <r>    -2.8590    59.8613   492.0309 </r>
       <r>    -2.6018    67.0108   509.2700 </r>
       <r>    -2.3445    95.8134   533.9188 </r>
       <r>    -2.0873   128.9776   567.0993 </r>
       <r>    -1.8300   163.9134   609.2674 </r>
       <r>    -1.5727   165.5975   651.8688 </r>
       <r>    -1.3155   144.0089   688.9163 </r>
       <r>    -1.0582   120.4961   719.9149 </r>
       <r>    -0.8010   113.8488   749.2035 </r>
       <r>    -0.5437    93.4008   773.2316 </r>
       <r>    -0.2865    75.4495   792.6416 </r>
       <r>    -0.0292    64.6796   809.2810 </r>
       <r>     0.2281    51.3542   822.4923 </r>
       <r>     0.4853    51.5806   835.7618 </r>
       <r>     0.7426    57.3480   850.5151 </r>
       <r>     0.9998    57.0759   865.1983 </r>
       <r>     1.2571    25.2092   871.6836 </r>
       <r>     1.5144    11.0048   874.5147 </r>
       <r>     1.7716    10.8775   877.3130 </r>
       <r>     2.0289     2.6072   877.9837 </r>
       <r>     2.2861     0.9379   878.2250 </r>
       <r>     2.5434     8.1049   880.3101 </r>
       <r>     2.8006    11.7225   883.3258 </r>
       <r>     3.0579     7.1049   885.1536 </r>
       <r>     3.3152    10.4347   887.8380 </r>
       <r>     3.5724    10.3005   890.4879 </r>
       <r>     3.8297    13.8335   894.0467 </r>
       <r>     4.0869    24.2049   900.2736 </r>
       <r>     4.3442    31.1131   908.2777 </r>
       <r>     4.6015    36.0172   917.5435 </r>
       <r>     4.8587    32.9851   926.0292 </r>
       <r>     5.1160    27.7023   933.1558 </r>
       <r>     5.3732    37.1247   942.7065 </r>
       <r>     5.6305    44.7449   954.2175 </r>
       <r>     5.8877    20.6734   959.5359 </r>
       <r>     6.1450     1.7894   959.9962 </r>
       <r>     6.4023     0.0147   960.0000 </r>
       <r>     6.6595     0.0000   960.0000 </r>
       <r>     6.9168     0.0000   960.0000 </r>
       <r>     7.1740     0.0000   960.0000 </r>
       <r>     7.4313     0.0000   960.0000 </r>
       <r>     7.6886     0.0000   960.0000 </r>
       <r>     7.9458     0.0000   960.0000 </r>
       <r>     8.2031     0.0000   960.0000 </r>
       <r>     8.4603     0.0000   960.0000 </r>
       <r>     8.7176     0.0000   960.0000 </r>
       <r>     8.9748     0.0000   960.0000 </r>
       <r>     9.2321     0.0000   960.0000 </r>
      </set>
     </set>
    </array>
   </total>
  </dos>
 </calculation>
 <structure name="finalpos" >
  <crystal>
   <varray name="basis" >
    <v>      16.88469405       0.00000000       0.00000000 </v>
    <v>       0.00000000       9.57841000       0.00000000 </v>
    <v>       0.00000000       0.00000000      16.16908712 </v>
   </varray>
   <i name="volume">   2615.00256803 </i>
   <varray name="rec_basis" >
    <v>       0.05922524       0.00000000       0.00000000 </v>
    <v>       0.00000000       0.10440146       0.00000000 </v>
    <v>       0.00000000       0.00000000       0.06184641 </v>
   </varray>
  </crystal>
  <varray name="positions" >
   <v>       0.78004631       0.14529695       0.12058499 </v>
   <v>       0.26276233       0.64529695       0.02520102 </v>
   <v>       0.29733029       0.64529695       0.21596897 </v>
   <v>       0.43519032       0.14529695       0.05699568 </v>
   <v>       0.46975828       0.14529695       0.24776362 </v>
   <v>       0.95247430       0.64529695       0.15237965 </v>
   <v>       0.98704226       0.64529695       0.34314760 </v>
   <v>       0.12490229       0.14529695       0.18417431 </v>
   <v>       0.15947025       0.14529695       0.37494226 </v>
   <v>       0.60761831       0.64529695       0.08879033 </v>
   <v>       0.64218627       0.64529695       0.27955828 </v>
   <v>       0.90758278       0.01319395       0.09538397 </v>
   <v>       0.94215073       0.01319395       0.28615192 </v>
   <v>       0.39029880       0.51319395       0.00000000 </v>
   <v>       0.42486675       0.51319395       0.19076795 </v>
   <v>       0.45943471       0.51319395       0.38153589 </v>
   <v>       0.56272679       0.01319395       0.03179466 </v>
   <v>       0.59729475       0.01319395       0.22256261 </v>
   <v>       0.08001077       0.51319395       0.12717863 </v>
   <v>       0.11457873       0.51319395       0.31794658 </v>
   <v>       0.25243876       0.01319395       0.15897329 </v>
   <v>       0.28700672       0.01319395       0.34974124 </v>
   <v>       0.73515478       0.51319395       0.06358932 </v>
   <v>       0.76972274       0.51319395       0.25435726 </v>
   <v>       0.90758278       0.27739995       0.09538397 </v>
   <v>       0.94215073       0.27739995       0.28615192 </v>
   <v>       0.39029880       0.77739995       0.00000000 </v>
   <v>       0.42486675       0.77739995       0.19076795 </v>
   <v>       0.45943471       0.77739995       0.38153589 </v>
   <v>       0.56272679       0.27739995       0.03179466 </v>
   <v>       0.59729475       0.27739995       0.22256261 </v>
   <v>       0.08001077       0.77739995       0.12717863 </v>
   <v>       0.11457873       0.77739995       0.31794658 </v>
   <v>       0.25243876       0.27739995       0.15897329 </v>
   <v>       0.73515478       0.77739995       0.06358932 </v>
   <v>       0.76972274       0.77739995       0.25435726 </v>
   <v>       0.02602916       0.14529695       0.37317765 </v>
   <v>       0.99146121       0.14529695       0.18240970 </v>
   <v>       0.47417723       0.64529695       0.08702573 </v>
   <v>       0.50874518       0.64529695       0.27779368 </v>
   <v>       0.64660522       0.14529695       0.11882039 </v>
   <v>       0.68117318       0.14529695       0.30958834 </v>
   <v>       0.12932124       0.64529695       0.02343641 </v>
   <v>       0.16388920       0.64529695       0.21420436 </v>
   <v>       0.30174923       0.14529695       0.05523107 </v>
   <v>       0.33631719       0.14529695       0.24599902 </v>
   <v>       0.81903321       0.64529695       0.15061505 </v>
   <v>       0.85360117       0.64529695       0.34138299 </v>
   <v>       0.79449310       0.31351195       0.02373179 </v>
   <v>       0.82906105       0.31351195       0.21449973 </v>
   <v>       0.31177708       0.81351195       0.11911576 </v>
   <v>       0.34634503       0.81351195       0.30988371 </v>
   <v>       0.48420507       0.31351195       0.15091042 </v>
   <v>       0.51877303       0.31351195       0.34167837 </v>
   <v>       0.00148905       0.81351195       0.24629439 </v>
   <v>       0.96692109       0.81351195       0.05552644 </v>
   <v>       0.13934908       0.31351195       0.08732110 </v>
   <v>       0.17391704       0.31351195       0.27808905 </v>
   <v>       0.65663306       0.81351195       0.18270508 </v>
   <v>       0.69120102       0.81351195       0.37347302 </v>
   <v>       0.31177708       0.47708195       0.11911576 </v>
   <v>       0.34634503       0.47708195       0.30988371 </v>
   <v>       0.79449310       0.97708195       0.02373179 </v>
   <v>       0.82906105       0.97708195       0.21449973 </v>
   <v>       0.00148905       0.47708195       0.24629439 </v>
   <v>       0.96692109       0.47708195       0.05552644 </v>
   <v>       0.48420507       0.97708195       0.15091042 </v>
   <v>       0.51877303       0.97708195       0.34167837 </v>
   <v>       0.65663306       0.47708195       0.18270508 </v>
   <v>       0.69120102       0.47708195       0.37347302 </v>
   <v>       0.13934908       0.97708195       0.08732110 </v>
   <v>       0.17391704       0.97708195       0.27808905 </v>
  </varray>
 </structure>
</modeling>
